{"config":{"output_file":null,"full_docs":false,"pub_only":true,"reachable_only":true,"distro_crate":false,"signatures":false,"borrow_data":false},"version":"0.19.0","compilation":{"directory":"/Users/rodydavis/.cargo/registry/src/github.com-1ecc6299db9ec823/crossbeam-utils-0.7.2","program":"/Users/rodydavis/.rustup/toolchains/stable-x86_64-apple-darwin/bin/rls","arguments":["--crate-name","crossbeam_utils","/Users/rodydavis/.cargo/registry/src/github.com-1ecc6299db9ec823/crossbeam-utils-0.7.2/src/lib.rs","--json=diagnostic-rendered-ansi","--crate-type","lib","--emit=dep-info,metadata","-C","debuginfo=2","--cfg","feature=\"default\"","--cfg","feature=\"lazy_static\"","--cfg","feature=\"std\"","-C","metadata=e95cb7ad35209be3","-C","extra-filename=-e95cb7ad35209be3","--out-dir","/Users/rodydavis/Developer/GitHub/examples/flutter_ffi_plugin/dart_wasmer/target/rls/debug/deps","-L","dependency=/Users/rodydavis/Developer/GitHub/examples/flutter_ffi_plugin/dart_wasmer/target/rls/debug/deps","--extern","cfg_if=/Users/rodydavis/Developer/GitHub/examples/flutter_ffi_plugin/dart_wasmer/target/rls/debug/deps/libcfg_if-8095ac63dd0da737.rmeta","--extern","lazy_static=/Users/rodydavis/Developer/GitHub/examples/flutter_ffi_plugin/dart_wasmer/target/rls/debug/deps/liblazy_static-8e123c54698e3a37.rmeta","--cap-lints","allow","--cfg","has_min_const_fn","--cfg","has_atomic_u8","--cfg","has_atomic_u16","--cfg","has_atomic_u32","--cfg","has_atomic_u64","--error-format=json","--sysroot","/Users/rodydavis/.rustup/toolchains/stable-x86_64-apple-darwin"],"output":"/Users/rodydavis/Developer/GitHub/examples/flutter_ffi_plugin/dart_wasmer/target/rls/debug/deps/libcrossbeam_utils-e95cb7ad35209be3.rmeta"},"prelude":{"crate_id":{"name":"crossbeam_utils","disambiguator":[9701662205736921071,2588488314631365860]},"crate_root":"/Users/rodydavis/.cargo/registry/src/github.com-1ecc6299db9ec823/crossbeam-utils-0.7.2/src","external_crates":[{"file_name":"/Users/rodydavis/.cargo/registry/src/github.com-1ecc6299db9ec823/crossbeam-utils-0.7.2/src/lib.rs","num":1,"id":{"name":"std","disambiguator":[5808000563841838002,6875932327897409807]}},{"file_name":"/Users/rodydavis/.cargo/registry/src/github.com-1ecc6299db9ec823/crossbeam-utils-0.7.2/src/lib.rs","num":2,"id":{"name":"core","disambiguator":[5459908120384850477,15760959269387734159]}},{"file_name":"/Users/rodydavis/.cargo/registry/src/github.com-1ecc6299db9ec823/crossbeam-utils-0.7.2/src/lib.rs","num":3,"id":{"name":"compiler_builtins","disambiguator":[11826469219384905814,12486183027959381912]}},{"file_name":"/Users/rodydavis/.cargo/registry/src/github.com-1ecc6299db9ec823/crossbeam-utils-0.7.2/src/lib.rs","num":4,"id":{"name":"rustc_std_workspace_core","disambiguator":[5497990426549684121,15109235050116755313]}},{"file_name":"/Users/rodydavis/.cargo/registry/src/github.com-1ecc6299db9ec823/crossbeam-utils-0.7.2/src/lib.rs","num":5,"id":{"name":"alloc","disambiguator":[9495953968349266340,8510226981626586408]}},{"file_name":"/Users/rodydavis/.cargo/registry/src/github.com-1ecc6299db9ec823/crossbeam-utils-0.7.2/src/lib.rs","num":6,"id":{"name":"libc","disambiguator":[423181384897816611,2293857470463835221]}},{"file_name":"/Users/rodydavis/.cargo/registry/src/github.com-1ecc6299db9ec823/crossbeam-utils-0.7.2/src/lib.rs","num":7,"id":{"name":"unwind","disambiguator":[5608331764705855408,15392280463108098182]}},{"file_name":"/Users/rodydavis/.cargo/registry/src/github.com-1ecc6299db9ec823/crossbeam-utils-0.7.2/src/lib.rs","num":8,"id":{"name":"cfg_if","disambiguator":[14701876030349379005,4369912422515260820]}},{"file_name":"/Users/rodydavis/.cargo/registry/src/github.com-1ecc6299db9ec823/crossbeam-utils-0.7.2/src/lib.rs","num":9,"id":{"name":"backtrace","disambiguator":[8984243875435576741,4446548522921354]}},{"file_name":"/Users/rodydavis/.cargo/registry/src/github.com-1ecc6299db9ec823/crossbeam-utils-0.7.2/src/lib.rs","num":10,"id":{"name":"rustc_demangle","disambiguator":[4101421024496600006,15821692231896539213]}},{"file_name":"/Users/rodydavis/.cargo/registry/src/github.com-1ecc6299db9ec823/crossbeam-utils-0.7.2/src/lib.rs","num":11,"id":{"name":"backtrace_sys","disambiguator":[3079379191059796654,13101802771042696873]}},{"file_name":"/Users/rodydavis/.cargo/registry/src/github.com-1ecc6299db9ec823/crossbeam-utils-0.7.2/src/lib.rs","num":12,"id":{"name":"hashbrown","disambiguator":[7173097494859913114,11426318732171342333]}},{"file_name":"/Users/rodydavis/.cargo/registry/src/github.com-1ecc6299db9ec823/crossbeam-utils-0.7.2/src/lib.rs","num":13,"id":{"name":"rustc_std_workspace_alloc","disambiguator":[12351377766094969309,8390201886823579403]}},{"file_name":"/Users/rodydavis/.cargo/registry/src/github.com-1ecc6299db9ec823/crossbeam-utils-0.7.2/src/lib.rs","num":14,"id":{"name":"panic_unwind","disambiguator":[2739304812783641882,6504751215723634061]}},{"file_name":"/Users/rodydavis/.cargo/registry/src/github.com-1ecc6299db9ec823/crossbeam-utils-0.7.2/src/lib.rs","num":15,"id":{"name":"cfg_if","disambiguator":[10201928301582868305,15717936632155057518]}},{"file_name":"/Users/rodydavis/.cargo/registry/src/github.com-1ecc6299db9ec823/crossbeam-utils-0.7.2/src/lib.rs","num":16,"id":{"name":"lazy_static","disambiguator":[5447528554659399162,2961476109220051939]}}],"span":{"file_name":"/Users/rodydavis/.cargo/registry/src/github.com-1ecc6299db9ec823/crossbeam-utils-0.7.2/src/lib.rs","byte_start":0,"byte_end":1823,"line_start":1,"line_end":64,"column_start":1,"column_end":2}},"imports":[{"kind":"Use","ref_id":{"krate":0,"index":19},"span":{"file_name":"/Users/rodydavis/.cargo/registry/src/github.com-1ecc6299db9ec823/crossbeam-utils-0.7.2/src/atomic/mod.rs","byte_start":2601,"byte_end":2611,"line_start":24,"line_end":24,"column_start":28,"column_end":38},"alias_span":null,"name":"AtomicCell","value":"","parent":{"krate":0,"index":5}},{"kind":"Use","ref_id":{"krate":0,"index":90},"span":{"file_name":"/Users/rodydavis/.cargo/registry/src/github.com-1ecc6299db9ec823/crossbeam-utils-0.7.2/src/atomic/mod.rs","byte_start":2636,"byte_end":2649,"line_start":25,"line_end":25,"column_start":24,"column_end":37},"alias_span":null,"name":"AtomicConsume","value":"","parent":{"krate":0,"index":5}},{"kind":"Use","ref_id":{"krate":0,"index":238},"span":{"file_name":"/Users/rodydavis/.cargo/registry/src/github.com-1ecc6299db9ec823/crossbeam-utils-0.7.2/src/lib.rs","byte_start":1617,"byte_end":1628,"line_start":51,"line_end":51,"column_start":23,"column_end":34},"alias_span":null,"name":"CachePadded","value":"","parent":{"krate":0,"index":0}},{"kind":"Use","ref_id":{"krate":0,"index":133},"span":{"file_name":"/Users/rodydavis/.cargo/registry/src/github.com-1ecc6299db9ec823/crossbeam-utils-0.7.2/src/lib.rs","byte_start":1661,"byte_end":1668,"line_start":54,"line_end":54,"column_start":18,"column_end":25},"alias_span":null,"name":"Backoff","value":"","parent":{"krate":0,"index":0}},{"kind":"Use","ref_id":{"krate":0,"index":276},"span":{"file_name":"/Users/rodydavis/.cargo/registry/src/github.com-1ecc6299db9ec823/crossbeam-utils-0.7.2/src/sync/mod.rs","byte_start":8552485,"byte_end":8552491,"line_start":15,"line_end":15,"column_start":24,"column_end":30},"alias_span":null,"name":"Parker","value":"","parent":{"krate":0,"index":265}},{"kind":"Use","ref_id":{"krate":0,"index":287},"span":{"file_name":"/Users/rodydavis/.cargo/registry/src/github.com-1ecc6299db9ec823/crossbeam-utils-0.7.2/src/sync/mod.rs","byte_start":8552493,"byte_end":8552501,"line_start":15,"line_end":15,"column_start":32,"column_end":40},"alias_span":null,"name":"Unparker","value":"","parent":{"krate":0,"index":265}},{"kind":"Use","ref_id":{"krate":0,"index":337},"span":{"file_name":"/Users/rodydavis/.cargo/registry/src/github.com-1ecc6299db9ec823/crossbeam-utils-0.7.2/src/sync/mod.rs","byte_start":8552533,"byte_end":8552544,"line_start":16,"line_end":16,"column_start":30,"column_end":41},"alias_span":null,"name":"ShardedLock","value":"","parent":{"krate":0,"index":265}},{"kind":"Use","ref_id":{"krate":0,"index":375},"span":{"file_name":"/Users/rodydavis/.cargo/registry/src/github.com-1ecc6299db9ec823/crossbeam-utils-0.7.2/src/sync/mod.rs","byte_start":8552546,"byte_end":8552566,"line_start":16,"line_end":16,"column_start":43,"column_end":63},"alias_span":null,"name":"ShardedLockReadGuard","value":"","parent":{"krate":0,"index":265}},{"kind":"Use","ref_id":{"krate":0,"index":397},"span":{"file_name":"/Users/rodydavis/.cargo/registry/src/github.com-1ecc6299db9ec823/crossbeam-utils-0.7.2/src/sync/mod.rs","byte_start":8552568,"byte_end":8552589,"line_start":16,"line_end":16,"column_start":65,"column_end":86},"alias_span":null,"name":"ShardedLockWriteGuard","value":"","parent":{"krate":0,"index":265}},{"kind":"Use","ref_id":{"krate":0,"index":443},"span":{"file_name":"/Users/rodydavis/.cargo/registry/src/github.com-1ecc6299db9ec823/crossbeam-utils-0.7.2/src/sync/mod.rs","byte_start":8552618,"byte_end":8552627,"line_start":17,"line_end":17,"column_start":27,"column_end":36},"alias_span":null,"name":"WaitGroup","value":"","parent":{"krate":0,"index":265}}],"defs":[{"kind":"Mod","id":{"krate":0,"index":0},"span":{"file_name":"/Users/rodydavis/.cargo/registry/src/github.com-1ecc6299db9ec823/crossbeam-utils-0.7.2/src/lib.rs","byte_start":0,"byte_end":1823,"line_start":1,"line_end":64,"column_start":1,"column_end":2},"name":"","qualname":"::","value":"/Users/rodydavis/.cargo/registry/src/github.com-1ecc6299db9ec823/crossbeam-utils-0.7.2/src/lib.rs","parent":null,"children":[{"krate":0,"index":1},{"krate":0,"index":2},{"krate":0,"index":3},{"krate":0,"index":4},{"krate":0,"index":147},{"krate":0,"index":5},{"krate":0,"index":100},{"krate":0,"index":126},{"krate":0,"index":127},{"krate":0,"index":146},{"krate":0,"index":264},{"krate":0,"index":265},{"krate":0,"index":465}],"decl_id":null,"docs":" Miscellaneous tools for concurrent programming.","sig":null,"attributes":[{"value":"warn(missing_docs)","span":{"file_name":"/Users/rodydavis/.cargo/registry/src/github.com-1ecc6299db9ec823/crossbeam-utils-0.7.2/src/lib.rs","byte_start":1087,"byte_end":1109,"line_start":29,"line_end":29,"column_start":1,"column_end":23}},{"value":"warn(missing_debug_implementations)","span":{"file_name":"/Users/rodydavis/.cargo/registry/src/github.com-1ecc6299db9ec823/crossbeam-utils-0.7.2/src/lib.rs","byte_start":1110,"byte_end":1149,"line_start":30,"line_end":30,"column_start":1,"column_end":40}}]},{"kind":"Mod","id":{"krate":0,"index":5},"span":{"file_name":"/Users/rodydavis/.cargo/registry/src/github.com-1ecc6299db9ec823/crossbeam-utils-0.7.2/src/atomic/mod.rs","byte_start":0,"byte_end":0,"line_start":1,"line_end":1,"column_start":1,"column_end":1},"name":"atomic","qualname":"::atomic","value":"/Users/rodydavis/.cargo/registry/src/github.com-1ecc6299db9ec823/crossbeam-utils-0.7.2/src/atomic/mod.rs","parent":null,"children":[{"krate":0,"index":148},{"krate":0,"index":6},{"krate":0,"index":88},{"krate":0,"index":98},{"krate":0,"index":99}],"decl_id":null,"docs":" Atomic types.\n","sig":null,"attributes":[]},{"kind":"Struct","id":{"krate":0,"index":19},"span":{"file_name":"/Users/rodydavis/.cargo/registry/src/github.com-1ecc6299db9ec823/crossbeam-utils-0.7.2/src/atomic/atomic_cell.rs","byte_start":3736,"byte_end":3746,"line_start":27,"line_end":27,"column_start":12,"column_end":22},"name":"AtomicCell","qualname":"::atomic::atomic_cell::AtomicCell","value":"AtomicCell {  }","parent":null,"children":[{"krate":0,"index":21}],"decl_id":null,"docs":" A thread-safe mutable memory location.","sig":null,"attributes":[{"value":"repr(transparent)","span":{"file_name":"/Users/rodydavis/.cargo/registry/src/github.com-1ecc6299db9ec823/crossbeam-utils-0.7.2/src/atomic/atomic_cell.rs","byte_start":3704,"byte_end":3724,"line_start":26,"line_end":26,"column_start":1,"column_end":21}}]},{"kind":"Method","id":{"krate":0,"index":32},"span":{"file_name":"/Users/rodydavis/.cargo/registry/src/github.com-1ecc6299db9ec823/crossbeam-utils-0.7.2/src/atomic/atomic_cell.rs","byte_start":4906,"byte_end":4909,"line_start":71,"line_end":71,"column_start":18,"column_end":21},"name":"new","qualname":"<AtomicCell<T>>::new","value":"fn (val: T) -> AtomicCell<T>","parent":null,"children":[],"decl_id":null,"docs":" Creates a new atomic cell initialized with `val`.","sig":null,"attributes":[{"value":"cfg(has_min_const_fn)","span":{"file_name":"/Users/rodydavis/.cargo/registry/src/github.com-1ecc6299db9ec823/crossbeam-utils-0.7.2/src/atomic/atomic_cell.rs","byte_start":4864,"byte_end":4888,"line_start":70,"line_end":70,"column_start":5,"column_end":29}}]},{"kind":"Method","id":{"krate":0,"index":33},"span":{"file_name":"/Users/rodydavis/.cargo/registry/src/github.com-1ecc6299db9ec823/crossbeam-utils-0.7.2/src/atomic/atomic_cell.rs","byte_start":5310,"byte_end":5320,"line_start":89,"line_end":89,"column_start":12,"column_end":22},"name":"into_inner","qualname":"<AtomicCell<T>>::into_inner","value":"fn (self) -> T","parent":null,"children":[],"decl_id":null,"docs":" Unwraps the atomic cell and returns its inner value.","sig":null,"attributes":[]},{"kind":"Method","id":{"krate":0,"index":34},"span":{"file_name":"/Users/rodydavis/.cargo/registry/src/github.com-1ecc6299db9ec823/crossbeam-utils-0.7.2/src/atomic/atomic_cell.rs","byte_start":6595,"byte_end":6607,"line_start":121,"line_end":121,"column_start":12,"column_end":24},"name":"is_lock_free","qualname":"<AtomicCell<T>>::is_lock_free","value":"fn () -> bool","parent":null,"children":[],"decl_id":null,"docs":" Returns `true` if operations on values of this type are lock-free.","sig":null,"attributes":[]},{"kind":"Method","id":{"krate":0,"index":35},"span":{"file_name":"/Users/rodydavis/.cargo/registry/src/github.com-1ecc6299db9ec823/crossbeam-utils-0.7.2/src/atomic/atomic_cell.rs","byte_start":6962,"byte_end":6967,"line_start":138,"line_end":138,"column_start":12,"column_end":17},"name":"store","qualname":"<AtomicCell<T>>::store","value":"fn (&self, val: T) -> ()","parent":null,"children":[],"decl_id":null,"docs":" Stores `val` into the atomic cell.","sig":null,"attributes":[]},{"kind":"Method","id":{"krate":0,"index":36},"span":{"file_name":"/Users/rodydavis/.cargo/registry/src/github.com-1ecc6299db9ec823/crossbeam-utils-0.7.2/src/atomic/atomic_cell.rs","byte_start":7522,"byte_end":7526,"line_start":161,"line_end":161,"column_start":12,"column_end":16},"name":"swap","qualname":"<AtomicCell<T>>::swap","value":"fn (&self, val: T) -> T","parent":null,"children":[],"decl_id":null,"docs":" Stores `val` into the atomic cell and returns the previous value.","sig":null,"attributes":[]},{"kind":"Method","id":{"krate":0,"index":39},"span":{"file_name":"/Users/rodydavis/.cargo/registry/src/github.com-1ecc6299db9ec823/crossbeam-utils-0.7.2/src/atomic/atomic_cell.rs","byte_start":7937,"byte_end":7943,"line_start":179,"line_end":179,"column_start":12,"column_end":18},"name":"as_ptr","qualname":"<AtomicCell<T>>::as_ptr","value":"fn (&self) -> *mut T","parent":null,"children":[],"decl_id":null,"docs":" Returns a raw pointer to the underlying data in this atomic cell.","sig":null,"attributes":[{"value":"inline","span":{"file_name":"/Users/rodydavis/.cargo/registry/src/github.com-1ecc6299db9ec823/crossbeam-utils-0.7.2/src/atomic/atomic_cell.rs","byte_start":7916,"byte_end":7925,"line_start":178,"line_end":178,"column_start":5,"column_end":14}}]},{"kind":"Method","id":{"krate":0,"index":40},"span":{"file_name":"/Users/rodydavis/.cargo/registry/src/github.com-1ecc6299db9ec823/crossbeam-utils-0.7.2/src/atomic/atomic_cell.rs","byte_start":8396,"byte_end":8403,"line_start":197,"line_end":197,"column_start":12,"column_end":19},"name":"get_mut","qualname":"<AtomicCell<T>>::get_mut","value":"fn (&mut self) -> &mut T","parent":null,"children":[],"decl_id":null,"docs":" Returns a mutable reference to the inner value.","sig":null,"attributes":[{"value":"deprecated(note =\n             \"this method is unsound and will be removed in the next release\")","span":{"file_name":"/Users/rodydavis/.cargo/registry/src/github.com-1ecc6299db9ec823/crossbeam-utils-0.7.2/src/atomic/atomic_cell.rs","byte_start":8298,"byte_end":8384,"line_start":196,"line_end":196,"column_start":5,"column_end":91}}]},{"kind":"Method","id":{"krate":0,"index":43},"span":{"file_name":"/Users/rodydavis/.cargo/registry/src/github.com-1ecc6299db9ec823/crossbeam-utils-0.7.2/src/atomic/atomic_cell.rs","byte_start":8866,"byte_end":8870,"line_start":216,"line_end":216,"column_start":12,"column_end":16},"name":"take","qualname":"<AtomicCell<T>>::take","value":"fn (&self) -> T","parent":null,"children":[],"decl_id":null,"docs":" Takes the value of the atomic cell, leaving `Default::default()` in its place.","sig":null,"attributes":[]},{"kind":"Method","id":{"krate":0,"index":46},"span":{"file_name":"/Users/rodydavis/.cargo/registry/src/github.com-1ecc6299db9ec823/crossbeam-utils-0.7.2/src/atomic/atomic_cell.rs","byte_start":9189,"byte_end":9193,"line_start":233,"line_end":233,"column_start":12,"column_end":16},"name":"load","qualname":"<AtomicCell<T>>::load","value":"fn (&self) -> T","parent":null,"children":[],"decl_id":null,"docs":" Loads a value.","sig":null,"attributes":[]},{"kind":"Method","id":{"krate":0,"index":49},"span":{"file_name":"/Users/rodydavis/.cargo/registry/src/github.com-1ecc6299db9ec823/crossbeam-utils-0.7.2/src/atomic/atomic_cell.rs","byte_start":9854,"byte_end":9870,"line_start":257,"line_end":257,"column_start":12,"column_end":28},"name":"compare_and_swap","qualname":"<AtomicCell<T>>::compare_and_swap","value":"fn (&self, current: T, new: T) -> T","parent":null,"children":[],"decl_id":null,"docs":" If the current value equals `current`, stores `new` into the atomic cell.","sig":null,"attributes":[]},{"kind":"Method","id":{"krate":0,"index":50},"span":{"file_name":"/Users/rodydavis/.cargo/registry/src/github.com-1ecc6299db9ec823/crossbeam-utils-0.7.2/src/atomic/atomic_cell.rs","byte_start":10652,"byte_end":10668,"line_start":282,"line_end":282,"column_start":12,"column_end":28},"name":"compare_exchange","qualname":"<AtomicCell<T>>::compare_exchange","value":"fn (&self, current: T, new: T) -> Result<T, T>","parent":null,"children":[],"decl_id":null,"docs":" If the current value equals `current`, stores `new` into the atomic cell.","sig":null,"attributes":[]},{"kind":"Method","id":{"krate":0,"index":53},"span":{"file_name":"/Users/rodydavis/.cargo/registry/src/github.com-1ecc6299db9ec823/crossbeam-utils-0.7.2/src/atomic/atomic_cell.rs","byte_start":20971,"byte_end":20980,"line_start":573,"line_end":573,"column_start":12,"column_end":21},"name":"fetch_and","qualname":"<AtomicCell<bool>>::fetch_and","value":"fn (&self, val: bool) -> bool","parent":null,"children":[],"decl_id":null,"docs":" Applies logical \"and\" to the current value and returns the previous value.","sig":null,"attributes":[{"value":"inline","span":{"file_name":"/Users/rodydavis/.cargo/registry/src/github.com-1ecc6299db9ec823/crossbeam-utils-0.7.2/src/atomic/atomic_cell.rs","byte_start":20950,"byte_end":20959,"line_start":572,"line_end":572,"column_start":5,"column_end":14}}]},{"kind":"Method","id":{"krate":0,"index":54},"span":{"file_name":"/Users/rodydavis/.cargo/registry/src/github.com-1ecc6299db9ec823/crossbeam-utils-0.7.2/src/atomic/atomic_cell.rs","byte_start":21572,"byte_end":21580,"line_start":594,"line_end":594,"column_start":12,"column_end":20},"name":"fetch_or","qualname":"<AtomicCell<bool>>::fetch_or","value":"fn (&self, val: bool) -> bool","parent":null,"children":[],"decl_id":null,"docs":" Applies logical \"or\" to the current value and returns the previous value.","sig":null,"attributes":[{"value":"inline","span":{"file_name":"/Users/rodydavis/.cargo/registry/src/github.com-1ecc6299db9ec823/crossbeam-utils-0.7.2/src/atomic/atomic_cell.rs","byte_start":21551,"byte_end":21560,"line_start":593,"line_end":593,"column_start":5,"column_end":14}}]},{"kind":"Method","id":{"krate":0,"index":55},"span":{"file_name":"/Users/rodydavis/.cargo/registry/src/github.com-1ecc6299db9ec823/crossbeam-utils-0.7.2/src/atomic/atomic_cell.rs","byte_start":22171,"byte_end":22180,"line_start":615,"line_end":615,"column_start":12,"column_end":21},"name":"fetch_xor","qualname":"<AtomicCell<bool>>::fetch_xor","value":"fn (&self, val: bool) -> bool","parent":null,"children":[],"decl_id":null,"docs":" Applies logical \"xor\" to the current value and returns the previous value.","sig":null,"attributes":[{"value":"inline","span":{"file_name":"/Users/rodydavis/.cargo/registry/src/github.com-1ecc6299db9ec823/crossbeam-utils-0.7.2/src/atomic/atomic_cell.rs","byte_start":22150,"byte_end":22159,"line_start":614,"line_end":614,"column_start":5,"column_end":14}}]},{"kind":"Trait","id":{"krate":0,"index":90},"span":{"file_name":"/Users/rodydavis/.cargo/registry/src/github.com-1ecc6299db9ec823/crossbeam-utils-0.7.2/src/atomic/consume.rs","byte_start":32016,"byte_end":32029,"line_start":6,"line_end":6,"column_start":11,"column_end":24},"name":"AtomicConsume","qualname":"::atomic::consume::AtomicConsume","value":"AtomicConsume","parent":null,"children":[{"krate":0,"index":91},{"krate":0,"index":92}],"decl_id":null,"docs":" Trait which allows reading from primitive atomic types with \"consume\" ordering.\n","sig":null,"attributes":[]},{"kind":"Type","id":{"krate":0,"index":91},"span":{"file_name":"/Users/rodydavis/.cargo/registry/src/github.com-1ecc6299db9ec823/crossbeam-utils-0.7.2/src/atomic/consume.rs","byte_start":32082,"byte_end":32085,"line_start":8,"line_end":8,"column_start":10,"column_end":13},"name":"Val","qualname":"::atomic::consume::AtomicConsume::Val","value":"type Val;","parent":{"krate":0,"index":90},"children":[],"decl_id":null,"docs":" Type returned by `load_consume`.\n","sig":null,"attributes":[]},{"kind":"Method","id":{"krate":0,"index":92},"span":{"file_name":"/Users/rodydavis/.cargo/registry/src/github.com-1ecc6299db9ec823/crossbeam-utils-0.7.2/src/atomic/consume.rs","byte_start":32923,"byte_end":32935,"line_start":25,"line_end":25,"column_start":8,"column_end":20},"name":"load_consume","qualname":"::atomic::consume::AtomicConsume::load_consume","value":"fn (&self) -> Self::Val","parent":{"krate":0,"index":90},"children":[],"decl_id":null,"docs":" Loads a value from the atomic using a \"consume\" memory ordering.","sig":null,"attributes":[]},{"kind":"Struct","id":{"krate":0,"index":238},"span":{"file_name":"/Users/rodydavis/.cargo/registry/src/github.com-1ecc6299db9ec823/crossbeam-utils-0.7.2/src/cache_padded.rs","byte_start":37269,"byte_end":37280,"line_start":68,"line_end":68,"column_start":12,"column_end":23},"name":"CachePadded","qualname":"::cache_padded::CachePadded","value":"CachePadded {  }","parent":null,"children":[{"krate":0,"index":240}],"decl_id":null,"docs":" Pads and aligns a value to the length of a cache line.","sig":null,"attributes":[{"value":"repr(align (128))","span":{"file_name":"/Users/rodydavis/.cargo/registry/src/github.com-1ecc6299db9ec823/crossbeam-utils-0.7.2/src/cache_padded.rs","byte_start":37181,"byte_end":37197,"line_start":66,"line_end":66,"column_start":36,"column_end":52}}]},{"kind":"Method","id":{"krate":0,"index":111},"span":{"file_name":"/Users/rodydavis/.cargo/registry/src/github.com-1ecc6299db9ec823/crossbeam-utils-0.7.2/src/cache_padded.rs","byte_start":37656,"byte_end":37659,"line_start":85,"line_end":85,"column_start":12,"column_end":15},"name":"new","qualname":"<CachePadded<T>>::new","value":"fn (t: T) -> CachePadded<T>","parent":null,"children":[],"decl_id":null,"docs":" Pads and aligns a value to the length of a cache line.","sig":null,"attributes":[]},{"kind":"Method","id":{"krate":0,"index":112},"span":{"file_name":"/Users/rodydavis/.cargo/registry/src/github.com-1ecc6299db9ec823/crossbeam-utils-0.7.2/src/cache_padded.rs","byte_start":38009,"byte_end":38019,"line_start":100,"line_end":100,"column_start":12,"column_end":22},"name":"into_inner","qualname":"<CachePadded<T>>::into_inner","value":"fn (self) -> T","parent":null,"children":[],"decl_id":null,"docs":" Returns the inner value.","sig":null,"attributes":[]},{"kind":"Struct","id":{"krate":0,"index":133},"span":{"file_name":"/Users/rodydavis/.cargo/registry/src/github.com-1ecc6299db9ec823/crossbeam-utils-0.7.2/src/backoff.rs","byte_start":41090,"byte_end":41097,"line_start":80,"line_end":80,"column_start":12,"column_end":19},"name":"Backoff","qualname":"::backoff::Backoff","value":"Backoff {  }","parent":null,"children":[{"krate":0,"index":134}],"decl_id":null,"docs":" Performs exponential backoff in spin loops.","sig":null,"attributes":[]},{"kind":"Method","id":{"krate":0,"index":136},"span":{"file_name":"/Users/rodydavis/.cargo/registry/src/github.com-1ecc6299db9ec823/crossbeam-utils-0.7.2/src/backoff.rs","byte_start":41340,"byte_end":41343,"line_start":95,"line_end":95,"column_start":12,"column_end":15},"name":"new","qualname":"<Backoff>::new","value":"fn () -> Self","parent":null,"children":[],"decl_id":null,"docs":" Creates a new `Backoff`.","sig":null,"attributes":[{"value":"inline","span":{"file_name":"/Users/rodydavis/.cargo/registry/src/github.com-1ecc6299db9ec823/crossbeam-utils-0.7.2/src/backoff.rs","byte_start":41319,"byte_end":41328,"line_start":94,"line_end":94,"column_start":5,"column_end":14}}]},{"kind":"Method","id":{"krate":0,"index":137},"span":{"file_name":"/Users/rodydavis/.cargo/registry/src/github.com-1ecc6299db9ec823/crossbeam-utils-0.7.2/src/backoff.rs","byte_start":41625,"byte_end":41630,"line_start":110,"line_end":110,"column_start":12,"column_end":17},"name":"reset","qualname":"<Backoff>::reset","value":"fn (&self) -> ()","parent":null,"children":[],"decl_id":null,"docs":" Resets the `Backoff`.","sig":null,"attributes":[{"value":"inline","span":{"file_name":"/Users/rodydavis/.cargo/registry/src/github.com-1ecc6299db9ec823/crossbeam-utils-0.7.2/src/backoff.rs","byte_start":41604,"byte_end":41613,"line_start":109,"line_end":109,"column_start":5,"column_end":14}}]},{"kind":"Method","id":{"krate":0,"index":138},"span":{"file_name":"/Users/rodydavis/.cargo/registry/src/github.com-1ecc6299db9ec823/crossbeam-utils-0.7.2/src/backoff.rs","byte_start":42665,"byte_end":42669,"line_start":146,"line_end":146,"column_start":12,"column_end":16},"name":"spin","qualname":"<Backoff>::spin","value":"fn (&self) -> ()","parent":null,"children":[],"decl_id":null,"docs":" Backs off in a lock-free loop.","sig":null,"attributes":[{"value":"inline","span":{"file_name":"/Users/rodydavis/.cargo/registry/src/github.com-1ecc6299db9ec823/crossbeam-utils-0.7.2/src/backoff.rs","byte_start":42644,"byte_end":42653,"line_start":145,"line_end":145,"column_start":5,"column_end":14}}]},{"kind":"Method","id":{"krate":0,"index":139},"span":{"file_name":"/Users/rodydavis/.cargo/registry/src/github.com-1ecc6299db9ec823/crossbeam-utils-0.7.2/src/backoff.rs","byte_start":44625,"byte_end":44631,"line_start":205,"line_end":205,"column_start":12,"column_end":18},"name":"snooze","qualname":"<Backoff>::snooze","value":"fn (&self) -> ()","parent":null,"children":[],"decl_id":null,"docs":" Backs off in a blocking loop.","sig":null,"attributes":[{"value":"inline","span":{"file_name":"/Users/rodydavis/.cargo/registry/src/github.com-1ecc6299db9ec823/crossbeam-utils-0.7.2/src/backoff.rs","byte_start":44604,"byte_end":44613,"line_start":204,"line_end":204,"column_start":5,"column_end":14}}]},{"kind":"Method","id":{"krate":0,"index":140},"span":{"file_name":"/Users/rodydavis/.cargo/registry/src/github.com-1ecc6299db9ec823/crossbeam-utils-0.7.2/src/backoff.rs","byte_start":46511,"byte_end":46523,"line_start":267,"line_end":267,"column_start":12,"column_end":24},"name":"is_completed","qualname":"<Backoff>::is_completed","value":"fn (&self) -> bool","parent":null,"children":[],"decl_id":null,"docs":" Returns `true` if exponential backoff has completed and blocking the thread is advised.","sig":null,"attributes":[{"value":"inline","span":{"file_name":"/Users/rodydavis/.cargo/registry/src/github.com-1ecc6299db9ec823/crossbeam-utils-0.7.2/src/backoff.rs","byte_start":46490,"byte_end":46499,"line_start":266,"line_end":266,"column_start":5,"column_end":14}}]},{"kind":"Method","id":{"krate":0,"index":141},"span":{"file_name":"/Users/rodydavis/.cargo/registry/src/github.com-1ecc6299db9ec823/crossbeam-utils-0.7.2/src/backoff.rs","byte_start":46685,"byte_end":46696,"line_start":274,"line_end":274,"column_start":12,"column_end":23},"name":"is_complete","qualname":"<Backoff>::is_complete","value":"fn (&self) -> bool","parent":null,"children":[],"decl_id":null,"docs":"","sig":null,"attributes":[{"value":"inline","span":{"file_name":"/Users/rodydavis/.cargo/registry/src/github.com-1ecc6299db9ec823/crossbeam-utils-0.7.2/src/backoff.rs","byte_start":46590,"byte_end":46599,"line_start":271,"line_end":271,"column_start":5,"column_end":14}},{"value":"deprecated(note = \"use `is_completed` instead\")","span":{"file_name":"/Users/rodydavis/.cargo/registry/src/github.com-1ecc6299db9ec823/crossbeam-utils-0.7.2/src/backoff.rs","byte_start":46623,"byte_end":46673,"line_start":273,"line_end":273,"column_start":5,"column_end":55}}]},{"kind":"Mod","id":{"krate":0,"index":265},"span":{"file_name":"/Users/rodydavis/.cargo/registry/src/github.com-1ecc6299db9ec823/crossbeam-utils-0.7.2/src/sync/mod.rs","byte_start":0,"byte_end":0,"line_start":1,"line_end":1,"column_start":1,"column_end":1},"name":"sync","qualname":"::sync","value":"/Users/rodydavis/.cargo/registry/src/github.com-1ecc6299db9ec823/crossbeam-utils-0.7.2/src/sync/mod.rs","parent":null,"children":[{"krate":0,"index":266},{"krate":0,"index":307},{"krate":0,"index":437},{"krate":0,"index":457},{"krate":0,"index":460},{"krate":0,"index":464}],"decl_id":null,"docs":" Thread synchronization primitives.","sig":null,"attributes":[]},{"kind":"Struct","id":{"krate":0,"index":276},"span":{"file_name":"/Users/rodydavis/.cargo/registry/src/github.com-1ecc6299db9ec823/crossbeam-utils-0.7.2/src/sync/parker.rs","byte_start":8554385,"byte_end":8554391,"line_start":54,"line_end":54,"column_start":12,"column_end":18},"name":"Parker","qualname":"::sync::parker::Parker","value":"Parker {  }","parent":null,"children":[{"krate":0,"index":277},{"krate":0,"index":278}],"decl_id":null,"docs":" A thread parking primitive.","sig":null,"attributes":[]},{"kind":"Method","id":{"krate":0,"index":281},"span":{"file_name":"/Users/rodydavis/.cargo/registry/src/github.com-1ecc6299db9ec823/crossbeam-utils-0.7.2/src/sync/parker.rs","byte_start":8554696,"byte_end":8554699,"line_start":72,"line_end":72,"column_start":12,"column_end":15},"name":"new","qualname":"<Parker>::new","value":"fn () -> Parker","parent":null,"children":[],"decl_id":null,"docs":" Creates a new `Parker`.","sig":null,"attributes":[]},{"kind":"Method","id":{"krate":0,"index":282},"span":{"file_name":"/Users/rodydavis/.cargo/registry/src/github.com-1ecc6299db9ec823/crossbeam-utils-0.7.2/src/sync/parker.rs","byte_start":8555582,"byte_end":8555586,"line_start":104,"line_end":104,"column_start":12,"column_end":16},"name":"park","qualname":"<Parker>::park","value":"fn (&self) -> ()","parent":null,"children":[],"decl_id":null,"docs":" Blocks the current thread until the token is made available.","sig":null,"attributes":[]},{"kind":"Method","id":{"krate":0,"index":283},"span":{"file_name":"/Users/rodydavis/.cargo/registry/src/github.com-1ecc6299db9ec823/crossbeam-utils-0.7.2/src/sync/parker.rs","byte_start":8556234,"byte_end":8556246,"line_start":124,"line_end":124,"column_start":12,"column_end":24},"name":"park_timeout","qualname":"<Parker>::park_timeout","value":"fn (&self, timeout: Duration) -> ()","parent":null,"children":[],"decl_id":null,"docs":" Blocks the current thread until the token is made available, but only for a limited time.","sig":null,"attributes":[]},{"kind":"Method","id":{"krate":0,"index":284},"span":{"file_name":"/Users/rodydavis/.cargo/registry/src/github.com-1ecc6299db9ec823/crossbeam-utils-0.7.2/src/sync/parker.rs","byte_start":8557000,"byte_end":8557008,"line_start":150,"line_end":150,"column_start":12,"column_end":20},"name":"unparker","qualname":"<Parker>::unparker","value":"fn (&self) -> &Unparker","parent":null,"children":[],"decl_id":null,"docs":" Returns a reference to an associated [`Unparker`].","sig":null,"attributes":[]},{"kind":"Struct","id":{"krate":0,"index":287},"span":{"file_name":"/Users/rodydavis/.cargo/registry/src/github.com-1ecc6299db9ec823/crossbeam-utils-0.7.2/src/sync/parker.rs","byte_start":8557299,"byte_end":8557307,"line_start":164,"line_end":164,"column_start":12,"column_end":20},"name":"Unparker","qualname":"::sync::parker::Unparker","value":"Unparker {  }","parent":null,"children":[{"krate":0,"index":288}],"decl_id":null,"docs":" Unparks a thread parked by the associated [`Parker`].","sig":null,"attributes":[]},{"kind":"Method","id":{"krate":0,"index":292},"span":{"file_name":"/Users/rodydavis/.cargo/registry/src/github.com-1ecc6299db9ec823/crossbeam-utils-0.7.2/src/sync/parker.rs","byte_start":8558277,"byte_end":8558283,"line_start":199,"line_end":199,"column_start":12,"column_end":18},"name":"unpark","qualname":"<Unparker>::unpark","value":"fn (&self) -> ()","parent":null,"children":[],"decl_id":null,"docs":" Atomically makes the token available if it is not already.","sig":null,"attributes":[]},{"kind":"Struct","id":{"krate":0,"index":337},"span":{"file_name":"/Users/rodydavis/.cargo/registry/src/github.com-1ecc6299db9ec823/crossbeam-utils-0.7.2/src/sync/sharded_lock.rs","byte_start":8565623,"byte_end":8565634,"line_start":75,"line_end":75,"column_start":12,"column_end":23},"name":"ShardedLock","qualname":"::sync::sharded_lock::ShardedLock","value":"ShardedLock {  }","parent":null,"children":[{"krate":0,"index":339},{"krate":0,"index":340}],"decl_id":null,"docs":" A sharded reader-writer lock.","sig":null,"attributes":[]},{"kind":"Method","id":{"krate":0,"index":351},"span":{"file_name":"/Users/rodydavis/.cargo/registry/src/github.com-1ecc6299db9ec823/crossbeam-utils-0.7.2/src/sync/sharded_lock.rs","byte_start":8566263,"byte_end":8566266,"line_start":99,"line_end":99,"column_start":12,"column_end":15},"name":"new","qualname":"<ShardedLock<T>>::new","value":"fn (value: T) -> ShardedLock<T>","parent":null,"children":[],"decl_id":null,"docs":" Creates a new sharded reader-writer lock.","sig":null,"attributes":[]},{"kind":"Method","id":{"krate":0,"index":353},"span":{"file_name":"/Users/rodydavis/.cargo/registry/src/github.com-1ecc6299db9ec823/crossbeam-utils-0.7.2/src/sync/sharded_lock.rs","byte_start":8567248,"byte_end":8567258,"line_start":131,"line_end":131,"column_start":12,"column_end":22},"name":"into_inner","qualname":"<ShardedLock<T>>::into_inner","value":"fn (self) -> LockResult<T>","parent":null,"children":[],"decl_id":null,"docs":" Consumes this lock, returning the underlying data.","sig":null,"attributes":[]},{"kind":"Method","id":{"krate":0,"index":356},"span":{"file_name":"/Users/rodydavis/.cargo/registry/src/github.com-1ecc6299db9ec823/crossbeam-utils-0.7.2/src/sync/sharded_lock.rs","byte_start":8568235,"byte_end":8568246,"line_start":165,"line_end":165,"column_start":12,"column_end":23},"name":"is_poisoned","qualname":"<ShardedLock<T>>::is_poisoned","value":"fn (&self) -> bool","parent":null,"children":[],"decl_id":null,"docs":" Returns `true` if the lock is poisoned.","sig":null,"attributes":[]},{"kind":"Method","id":{"krate":0,"index":357},"span":{"file_name":"/Users/rodydavis/.cargo/registry/src/github.com-1ecc6299db9ec823/crossbeam-utils-0.7.2/src/sync/sharded_lock.rs","byte_start":8568860,"byte_end":8568867,"line_start":185,"line_end":185,"column_start":12,"column_end":19},"name":"get_mut","qualname":"<ShardedLock<T>>::get_mut","value":"fn (&mut self) -> LockResult<&mut T>","parent":null,"children":[],"decl_id":null,"docs":" Returns a mutable reference to the underlying data.","sig":null,"attributes":[]},{"kind":"Method","id":{"krate":0,"index":358},"span":{"file_name":"/Users/rodydavis/.cargo/registry/src/github.com-1ecc6299db9ec823/crossbeam-utils-0.7.2/src/sync/sharded_lock.rs","byte_start":8569962,"byte_end":8569970,"line_start":218,"line_end":218,"column_start":12,"column_end":20},"name":"try_read","qualname":"<ShardedLock<T>>::try_read","value":"fn (&self) -> TryLockResult<ShardedLockReadGuard<T>>","parent":null,"children":[],"decl_id":null,"docs":" Attempts to acquire this lock with shared read access.","sig":null,"attributes":[]},{"kind":"Method","id":{"krate":0,"index":359},"span":{"file_name":"/Users/rodydavis/.cargo/registry/src/github.com-1ecc6299db9ec823/crossbeam-utils-0.7.2/src/sync/sharded_lock.rs","byte_start":8571980,"byte_end":8571984,"line_start":269,"line_end":269,"column_start":12,"column_end":16},"name":"read","qualname":"<ShardedLock<T>>::read","value":"fn (&self) -> LockResult<ShardedLockReadGuard<T>>","parent":null,"children":[],"decl_id":null,"docs":" Locks with shared read access, blocking the current thread until it can be acquired.","sig":null,"attributes":[]},{"kind":"Method","id":{"krate":0,"index":360},"span":{"file_name":"/Users/rodydavis/.cargo/registry/src/github.com-1ecc6299db9ec823/crossbeam-utils-0.7.2/src/sync/sharded_lock.rs","byte_start":8573620,"byte_end":8573629,"line_start":311,"line_end":311,"column_start":12,"column_end":21},"name":"try_write","qualname":"<ShardedLock<T>>::try_write","value":"fn (&self) -> TryLockResult<ShardedLockWriteGuard<T>>","parent":null,"children":[],"decl_id":null,"docs":" Attempts to acquire this lock with exclusive write access.","sig":null,"attributes":[]},{"kind":"Method","id":{"krate":0,"index":361},"span":{"file_name":"/Users/rodydavis/.cargo/registry/src/github.com-1ecc6299db9ec823/crossbeam-utils-0.7.2/src/sync/sharded_lock.rs","byte_start":8576126,"byte_end":8576131,"line_start":382,"line_end":382,"column_start":12,"column_end":17},"name":"write","qualname":"<ShardedLock<T>>::write","value":"fn (&self) -> LockResult<ShardedLockWriteGuard<T>>","parent":null,"children":[],"decl_id":null,"docs":" Locks with exclusive write access, blocking the current thread until it can be acquired.","sig":null,"attributes":[]},{"kind":"Struct","id":{"krate":0,"index":375},"span":{"file_name":"/Users/rodydavis/.cargo/registry/src/github.com-1ecc6299db9ec823/crossbeam-utils-0.7.2/src/sync/sharded_lock.rs","byte_start":8578502,"byte_end":8578522,"line_start":459,"line_end":459,"column_start":12,"column_end":32},"name":"ShardedLockReadGuard","qualname":"::sync::sharded_lock::ShardedLockReadGuard","value":"ShardedLockReadGuard {  }","parent":null,"children":[{"krate":0,"index":378},{"krate":0,"index":379},{"krate":0,"index":380}],"decl_id":null,"docs":" A guard used to release the shared read access of a [`ShardedLock`] when dropped.","sig":null,"attributes":[]},{"kind":"Struct","id":{"krate":0,"index":397},"span":{"file_name":"/Users/rodydavis/.cargo/registry/src/github.com-1ecc6299db9ec823/crossbeam-utils-0.7.2/src/sync/sharded_lock.rs","byte_start":8579471,"byte_end":8579492,"line_start":492,"line_end":492,"column_start":12,"column_end":33},"name":"ShardedLockWriteGuard","qualname":"::sync::sharded_lock::ShardedLockWriteGuard","value":"ShardedLockWriteGuard {  }","parent":null,"children":[{"krate":0,"index":400},{"krate":0,"index":401}],"decl_id":null,"docs":" A guard used to release the exclusive write access of a [`ShardedLock`] when dropped.","sig":null,"attributes":[]},{"kind":"Struct","id":{"krate":0,"index":443},"span":{"file_name":"/Users/rodydavis/.cargo/registry/src/github.com-1ecc6299db9ec823/crossbeam-utils-0.7.2/src/sync/wait_group.rs","byte_start":8584035,"byte_end":8584044,"line_start":45,"line_end":45,"column_start":12,"column_end":21},"name":"WaitGroup","qualname":"::sync::wait_group::WaitGroup","value":"WaitGroup {  }","parent":null,"children":[{"krate":0,"index":444}],"decl_id":null,"docs":" Enables threads to synchronize the beginning or end of some computation.","sig":null,"attributes":[]},{"kind":"Method","id":{"krate":0,"index":449},"span":{"file_name":"/Users/rodydavis/.cargo/registry/src/github.com-1ecc6299db9ec823/crossbeam-utils-0.7.2/src/sync/wait_group.rs","byte_start":8584418,"byte_end":8584421,"line_start":65,"line_end":65,"column_start":12,"column_end":15},"name":"new","qualname":"<WaitGroup>::new","value":"fn () -> WaitGroup","parent":null,"children":[],"decl_id":null,"docs":" Creates a new wait group and returns the single reference to it.","sig":null,"attributes":[]},{"kind":"Method","id":{"krate":0,"index":450},"span":{"file_name":"/Users/rodydavis/.cargo/registry/src/github.com-1ecc6299db9ec823/crossbeam-utils-0.7.2/src/sync/wait_group.rs","byte_start":8585160,"byte_end":8585164,"line_start":95,"line_end":95,"column_start":12,"column_end":16},"name":"wait","qualname":"<WaitGroup>::wait","value":"fn (self) -> ()","parent":null,"children":[],"decl_id":null,"docs":" Drops this reference and waits until all other references are dropped.","sig":null,"attributes":[]},{"kind":"Mod","id":{"krate":0,"index":465},"span":{"file_name":"/Users/rodydavis/.cargo/registry/src/github.com-1ecc6299db9ec823/crossbeam-utils-0.7.2/src/thread.rs","byte_start":0,"byte_end":0,"line_start":1,"line_end":1,"column_start":1,"column_end":1},"name":"thread","qualname":"::thread","value":"/Users/rodydavis/.cargo/registry/src/github.com-1ecc6299db9ec823/crossbeam-utils-0.7.2/src/thread.rs","parent":null,"children":[{"krate":0,"index":466},{"krate":0,"index":467},{"krate":0,"index":468},{"krate":0,"index":469},{"krate":0,"index":470},{"krate":0,"index":471},{"krate":0,"index":474},{"krate":0,"index":475},{"krate":0,"index":476},{"krate":0,"index":478},{"krate":0,"index":480},{"krate":0,"index":487},{"krate":0,"index":492},{"krate":0,"index":494},{"krate":0,"index":502},{"krate":0,"index":554},{"krate":0,"index":559},{"krate":0,"index":505},{"krate":0,"index":516},{"krate":0,"index":519},{"krate":0,"index":522},{"krate":0,"index":529},{"krate":0,"index":535}],"decl_id":null,"docs":" Threads that can borrow variables from the stack.","sig":null,"attributes":[]},{"kind":"Function","id":{"krate":0,"index":480},"span":{"file_name":"/Users/rodydavis/.cargo/registry/src/github.com-1ecc6299db9ec823/crossbeam-utils-0.7.2/src/thread.rs","byte_start":8590602,"byte_end":8590607,"line_start":149,"line_end":149,"column_start":8,"column_end":13},"name":"scope","qualname":"::thread::scope","value":"fn <'env, F, R> (f: F) -> thread::Result<R>","parent":null,"children":[],"decl_id":null,"docs":" Creates a new scope for spawning threads.","sig":null,"attributes":[]},{"kind":"Struct","id":{"krate":0,"index":487},"span":{"file_name":"/Users/rodydavis/.cargo/registry/src/github.com-1ecc6299db9ec823/crossbeam-utils-0.7.2/src/thread.rs","byte_start":8591988,"byte_end":8591993,"line_start":197,"line_end":197,"column_start":12,"column_end":17},"name":"Scope","qualname":"::thread::Scope","value":"Scope {  }","parent":null,"children":[{"krate":0,"index":489},{"krate":0,"index":490},{"krate":0,"index":491}],"decl_id":null,"docs":" A scope for spawning threads.\n","sig":null,"attributes":[]},{"kind":"Method","id":{"krate":0,"index":496},"span":{"file_name":"/Users/rodydavis/.cargo/registry/src/github.com-1ecc6299db9ec823/crossbeam-utils-0.7.2/src/thread.rs","byte_start":8593419,"byte_end":8593424,"line_start":240,"line_end":240,"column_start":12,"column_end":17},"name":"spawn","qualname":"<Scope>::spawn","value":"fn <'scope, F, T> (&'scope self, f: F) -> ScopedJoinHandle<'scope, T>","parent":null,"children":[],"decl_id":null,"docs":" Spawns a scoped thread.","sig":null,"attributes":[]},{"kind":"Method","id":{"krate":0,"index":500},"span":{"file_name":"/Users/rodydavis/.cargo/registry/src/github.com-1ecc6299db9ec823/crossbeam-utils-0.7.2/src/thread.rs","byte_start":8594026,"byte_end":8594033,"line_start":263,"line_end":263,"column_start":12,"column_end":19},"name":"builder","qualname":"<Scope>::builder","value":"fn <'scope> (&'scope self) -> ScopedThreadBuilder<'scope, 'env>","parent":null,"children":[],"decl_id":null,"docs":" Creates a builder that can configure a thread before spawning.","sig":null,"attributes":[]},{"kind":"Struct","id":{"krate":0,"index":554},"span":{"file_name":"/Users/rodydavis/.cargo/registry/src/github.com-1ecc6299db9ec823/crossbeam-utils-0.7.2/src/thread.rs","byte_start":8595693,"byte_end":8595712,"line_start":311,"line_end":311,"column_start":12,"column_end":31},"name":"ScopedThreadBuilder","qualname":"::thread::ScopedThreadBuilder","value":"ScopedThreadBuilder {  }","parent":null,"children":[{"krate":0,"index":557},{"krate":0,"index":558}],"decl_id":null,"docs":" Configures the properties of a new thread.","sig":null,"attributes":[]},{"kind":"Method","id":{"krate":0,"index":508},"span":{"file_name":"/Users/rodydavis/.cargo/registry/src/github.com-1ecc6299db9ec823/crossbeam-utils-0.7.2/src/thread.rs","byte_start":8596500,"byte_end":8596504,"line_start":337,"line_end":337,"column_start":12,"column_end":16},"name":"name","qualname":"<ScopedThreadBuilder>::name","value":"fn (mut self, name: String) -> ScopedThreadBuilder<'scope, 'env>","parent":null,"children":[],"decl_id":null,"docs":" Sets the name for the new thread.","sig":null,"attributes":[]},{"kind":"Method","id":{"krate":0,"index":509},"span":{"file_name":"/Users/rodydavis/.cargo/registry/src/github.com-1ecc6299db9ec823/crossbeam-utils-0.7.2/src/thread.rs","byte_start":8597061,"byte_end":8597071,"line_start":358,"line_end":358,"column_start":12,"column_end":22},"name":"stack_size","qualname":"<ScopedThreadBuilder>::stack_size","value":"fn (mut self, size: usize) -> ScopedThreadBuilder<'scope, 'env>","parent":null,"children":[],"decl_id":null,"docs":" Sets the size of the stack for the new thread.","sig":null,"attributes":[]},{"kind":"Method","id":{"krate":0,"index":510},"span":{"file_name":"/Users/rodydavis/.cargo/registry/src/github.com-1ecc6299db9ec823/crossbeam-utils-0.7.2/src/thread.rs","byte_start":8598006,"byte_end":8598011,"line_start":388,"line_end":388,"column_start":12,"column_end":17},"name":"spawn","qualname":"<ScopedThreadBuilder>::spawn","value":"fn <F, T> (self, f: F) -> io::Result<ScopedJoinHandle<'scope, T>>","parent":null,"children":[],"decl_id":null,"docs":" Spawns a scoped thread with this configuration.","sig":null,"attributes":[]},{"kind":"Struct","id":{"krate":0,"index":522},"span":{"file_name":"/Users/rodydavis/.cargo/registry/src/github.com-1ecc6299db9ec823/crossbeam-utils-0.7.2/src/thread.rs","byte_start":8600439,"byte_end":8600455,"line_start":455,"line_end":455,"column_start":12,"column_end":28},"name":"ScopedJoinHandle","qualname":"::thread::ScopedJoinHandle","value":"ScopedJoinHandle {  }","parent":null,"children":[{"krate":0,"index":525},{"krate":0,"index":526},{"krate":0,"index":527},{"krate":0,"index":528}],"decl_id":null,"docs":" A handle that can be used to join its scoped thread.\n","sig":null,"attributes":[]},{"kind":"Method","id":{"krate":0,"index":532},"span":{"file_name":"/Users/rodydavis/.cargo/registry/src/github.com-1ecc6299db9ec823/crossbeam-utils-0.7.2/src/thread.rs","byte_start":8601775,"byte_end":8601779,"line_start":497,"line_end":497,"column_start":12,"column_end":16},"name":"join","qualname":"<ScopedJoinHandle>::join","value":"fn (self) -> thread::Result<T>","parent":null,"children":[],"decl_id":null,"docs":" Waits for the thread to finish and returns its result.","sig":null,"attributes":[]},{"kind":"Method","id":{"krate":0,"index":534},"span":{"file_name":"/Users/rodydavis/.cargo/registry/src/github.com-1ecc6299db9ec823/crossbeam-utils-0.7.2/src/thread.rs","byte_start":8602588,"byte_end":8602594,"line_start":520,"line_end":520,"column_start":12,"column_end":18},"name":"thread","qualname":"<ScopedJoinHandle>::thread","value":"fn (&self) -> &thread::Thread","parent":null,"children":[],"decl_id":null,"docs":" Returns a handle to the underlying thread.","sig":null,"attributes":[]}],"impls":[{"id":0,"kind":"Inherent","span":{"file_name":"/Users/rodydavis/.cargo/registry/src/github.com-1ecc6299db9ec823/crossbeam-utils-0.7.2/src/atomic/seq_lock.rs","byte_start":8549884,"byte_end":8549891,"line_start":14,"line_end":14,"column_start":6,"column_end":13},"value":"","parent":null,"children":[{"krate":0,"index":157},{"krate":0,"index":158},{"krate":0,"index":159},{"krate":0,"index":160}],"docs":"","sig":null,"attributes":[]},{"id":1,"kind":"Inherent","span":{"file_name":"/Users/rodydavis/.cargo/registry/src/github.com-1ecc6299db9ec823/crossbeam-utils-0.7.2/src/atomic/seq_lock.rs","byte_start":8551474,"byte_end":8551491,"line_start":72,"line_end":72,"column_start":6,"column_end":23},"value":"","parent":null,"children":[{"krate":0,"index":165}],"docs":"","sig":null,"attributes":[]},{"id":2,"kind":"Direct","span":{"file_name":"/Users/rodydavis/.cargo/registry/src/github.com-1ecc6299db9ec823/crossbeam-utils-0.7.2/src/atomic/seq_lock.rs","byte_start":8551676,"byte_end":8551693,"line_start":80,"line_end":80,"column_start":15,"column_end":32},"value":"","parent":null,"children":[{"krate":0,"index":167}],"docs":"","sig":null,"attributes":[]},{"id":3,"kind":"Direct","span":{"file_name":"/Users/rodydavis/.cargo/registry/src/github.com-1ecc6299db9ec823/crossbeam-utils-0.7.2/src/atomic/atomic_cell.rs","byte_start":4064,"byte_end":4074,"line_start":36,"line_end":36,"column_start":31,"column_end":41},"value":"","parent":null,"children":[],"docs":"","sig":null,"attributes":[]},{"id":4,"kind":"Direct","span":{"file_name":"/Users/rodydavis/.cargo/registry/src/github.com-1ecc6299db9ec823/crossbeam-utils-0.7.2/src/atomic/atomic_cell.rs","byte_start":4111,"byte_end":4121,"line_start":37,"line_end":37,"column_start":31,"column_end":41},"value":"","parent":null,"children":[],"docs":"","sig":null,"attributes":[]},{"id":5,"kind":"Direct","span":{"file_name":"/Users/rodydavis/.cargo/registry/src/github.com-1ecc6299db9ec823/crossbeam-utils-0.7.2/src/atomic/atomic_cell.rs","byte_start":4176,"byte_end":4186,"line_start":40,"line_end":40,"column_start":24,"column_end":34},"value":"","parent":null,"children":[],"docs":"","sig":null,"attributes":[]},{"id":6,"kind":"Direct","span":{"file_name":"/Users/rodydavis/.cargo/registry/src/github.com-1ecc6299db9ec823/crossbeam-utils-0.7.2/src/atomic/atomic_cell.rs","byte_start":4243,"byte_end":4253,"line_start":42,"line_end":42,"column_start":27,"column_end":37},"value":"","parent":null,"children":[],"docs":"","sig":null,"attributes":[]},{"id":7,"kind":"Inherent","span":{"file_name":"/Users/rodydavis/.cargo/registry/src/github.com-1ecc6299db9ec823/crossbeam-utils-0.7.2/src/atomic/atomic_cell.rs","byte_start":4269,"byte_end":4279,"line_start":44,"line_end":44,"column_start":9,"column_end":19},"value":"","parent":null,"children":[{"krate":0,"index":32},{"krate":0,"index":33},{"krate":0,"index":34},{"krate":0,"index":35},{"krate":0,"index":36}],"docs":"","sig":null,"attributes":[]},{"id":8,"kind":"Inherent","span":{"file_name":"/Users/rodydavis/.cargo/registry/src/github.com-1ecc6299db9ec823/crossbeam-utils-0.7.2/src/atomic/atomic_cell.rs","byte_start":7628,"byte_end":7638,"line_start":166,"line_end":166,"column_start":17,"column_end":27},"value":"","parent":null,"children":[{"krate":0,"index":39},{"krate":0,"index":40}],"docs":"","sig":null,"attributes":[]},{"id":9,"kind":"Inherent","span":{"file_name":"/Users/rodydavis/.cargo/registry/src/github.com-1ecc6299db9ec823/crossbeam-utils-0.7.2/src/atomic/atomic_cell.rs","byte_start":8495,"byte_end":8505,"line_start":202,"line_end":202,"column_start":18,"column_end":28},"value":"","parent":null,"children":[{"krate":0,"index":43}],"docs":"","sig":null,"attributes":[]},{"id":10,"kind":"Inherent","span":{"file_name":"/Users/rodydavis/.cargo/registry/src/github.com-1ecc6299db9ec823/crossbeam-utils-0.7.2/src/atomic/atomic_cell.rs","byte_start":8946,"byte_end":8956,"line_start":221,"line_end":221,"column_start":15,"column_end":25},"value":"","parent":null,"children":[{"krate":0,"index":46}],"docs":"","sig":null,"attributes":[]},{"id":11,"kind":"Inherent","span":{"file_name":"/Users/rodydavis/.cargo/registry/src/github.com-1ecc6299db9ec823/crossbeam-utils-0.7.2/src/atomic/atomic_cell.rs","byte_start":9285,"byte_end":9295,"line_start":238,"line_end":238,"column_start":20,"column_end":30},"value":"","parent":null,"children":[{"krate":0,"index":49},{"krate":0,"index":50}],"docs":"","sig":null,"attributes":[]},{"id":12,"kind":"Inherent","span":{"file_name":"/Users/rodydavis/.cargo/registry/src/github.com-1ecc6299db9ec823/crossbeam-utils-0.7.2/src/atomic/atomic_cell.rs","byte_start":20509,"byte_end":20519,"line_start":556,"line_end":556,"column_start":6,"column_end":16},"value":"","parent":null,"children":[{"krate":0,"index":53},{"krate":0,"index":54},{"krate":0,"index":55}],"docs":"","sig":null,"attributes":[]},{"id":13,"kind":"Direct","span":{"file_name":"/Users/rodydavis/.cargo/registry/src/github.com-1ecc6299db9ec823/crossbeam-utils-0.7.2/src/atomic/atomic_cell.rs","byte_start":22360,"byte_end":22370,"line_start":621,"line_end":621,"column_start":30,"column_end":40},"value":"","parent":null,"children":[{"krate":0,"index":58}],"docs":"","sig":null,"attributes":[]},{"id":14,"kind":"Direct","span":{"file_name":"/Users/rodydavis/.cargo/registry/src/github.com-1ecc6299db9ec823/crossbeam-utils-0.7.2/src/atomic/atomic_cell.rs","byte_start":22501,"byte_end":22511,"line_start":627,"line_end":627,"column_start":43,"column_end":53},"value":"","parent":null,"children":[{"krate":0,"index":61}],"docs":"","sig":null,"attributes":[]},{"id":15,"kind":"Inherent","span":{"file_name":"/Users/rodydavis/.cargo/registry/src/github.com-1ecc6299db9ec823/crossbeam-utils-0.7.2/src/atomic/atomic_cell.rs","byte_start":25262,"byte_end":25272,"line_start":695,"line_end":695,"column_start":6,"column_end":16},"value":"","parent":null,"children":[{"krate":0,"index":73},{"krate":0,"index":74},{"krate":0,"index":75},{"krate":0,"index":76}],"docs":"","sig":null,"attributes":[]},{"id":16,"kind":"Direct","span":{"file_name":"/Users/rodydavis/.cargo/registry/src/github.com-1ecc6299db9ec823/crossbeam-utils-0.7.2/src/atomic/consume.rs","byte_start":34548,"byte_end":34557,"line_start":79,"line_end":79,"column_start":49,"column_end":58},"value":"","parent":null,"children":[{"krate":0,"index":97},{"krate":0,"index":237}],"docs":"","sig":null,"attributes":[]},{"id":17,"kind":"Direct","span":{"file_name":"/Users/rodydavis/.cargo/registry/src/github.com-1ecc6299db9ec823/crossbeam-utils-0.7.2/src/cache_padded.rs","byte_start":37333,"byte_end":37344,"line_start":72,"line_end":72,"column_start":31,"column_end":42},"value":"","parent":null,"children":[],"docs":"","sig":null,"attributes":[]},{"id":18,"kind":"Direct","span":{"file_name":"/Users/rodydavis/.cargo/registry/src/github.com-1ecc6299db9ec823/crossbeam-utils-0.7.2/src/cache_padded.rs","byte_start":37381,"byte_end":37392,"line_start":73,"line_end":73,"column_start":31,"column_end":42},"value":"","parent":null,"children":[],"docs":"","sig":null,"attributes":[]},{"id":19,"kind":"Inherent","span":{"file_name":"/Users/rodydavis/.cargo/registry/src/github.com-1ecc6299db9ec823/crossbeam-utils-0.7.2/src/cache_padded.rs","byte_start":37408,"byte_end":37419,"line_start":75,"line_end":75,"column_start":9,"column_end":20},"value":"","parent":null,"children":[{"krate":0,"index":111},{"krate":0,"index":112}],"docs":"","sig":null,"attributes":[]},{"id":20,"kind":"Direct","span":{"file_name":"/Users/rodydavis/.cargo/registry/src/github.com-1ecc6299db9ec823/crossbeam-utils-0.7.2/src/cache_padded.rs","byte_start":38079,"byte_end":38090,"line_start":105,"line_end":105,"column_start":19,"column_end":30},"value":"","parent":null,"children":[{"krate":0,"index":115},{"krate":0,"index":116}],"docs":"","sig":null,"attributes":[]},{"id":21,"kind":"Direct","span":{"file_name":"/Users/rodydavis/.cargo/registry/src/github.com-1ecc6299db9ec823/crossbeam-utils-0.7.2/src/cache_padded.rs","byte_start":38196,"byte_end":38207,"line_start":113,"line_end":113,"column_start":22,"column_end":33},"value":"","parent":null,"children":[{"krate":0,"index":119}],"docs":"","sig":null,"attributes":[]},{"id":22,"kind":"Direct","span":{"file_name":"/Users/rodydavis/.cargo/registry/src/github.com-1ecc6299db9ec823/crossbeam-utils-0.7.2/src/cache_padded.rs","byte_start":38321,"byte_end":38332,"line_start":119,"line_end":119,"column_start":36,"column_end":47},"value":"","parent":null,"children":[{"krate":0,"index":122}],"docs":"","sig":null,"attributes":[]},{"id":23,"kind":"Direct","span":{"file_name":"/Users/rodydavis/.cargo/registry/src/github.com-1ecc6299db9ec823/crossbeam-utils-0.7.2/src/cache_padded.rs","byte_start":38527,"byte_end":38538,"line_start":127,"line_end":127,"column_start":21,"column_end":32},"value":"","parent":null,"children":[{"krate":0,"index":125}],"docs":"","sig":null,"attributes":[]},{"id":24,"kind":"Inherent","span":{"file_name":"/Users/rodydavis/.cargo/registry/src/github.com-1ecc6299db9ec823/crossbeam-utils-0.7.2/src/backoff.rs","byte_start":41129,"byte_end":41136,"line_start":84,"line_end":84,"column_start":6,"column_end":13},"value":"","parent":null,"children":[{"krate":0,"index":136},{"krate":0,"index":137},{"krate":0,"index":138},{"krate":0,"index":139},{"krate":0,"index":140},{"krate":0,"index":141}],"docs":"","sig":null,"attributes":[]},{"id":25,"kind":"Direct","span":{"file_name":"/Users/rodydavis/.cargo/registry/src/github.com-1ecc6299db9ec823/crossbeam-utils-0.7.2/src/backoff.rs","byte_start":46771,"byte_end":46778,"line_start":279,"line_end":279,"column_start":21,"column_end":28},"value":"","parent":null,"children":[{"krate":0,"index":143}],"docs":"","sig":null,"attributes":[]},{"id":26,"kind":"Direct","span":{"file_name":"/Users/rodydavis/.cargo/registry/src/github.com-1ecc6299db9ec823/crossbeam-utils-0.7.2/src/backoff.rs","byte_start":47018,"byte_end":47025,"line_start":288,"line_end":288,"column_start":18,"column_end":25},"value":"","parent":null,"children":[{"krate":0,"index":145}],"docs":"","sig":null,"attributes":[]},{"id":27,"kind":"Direct","span":{"file_name":"/Users/rodydavis/.cargo/registry/src/github.com-1ecc6299db9ec823/crossbeam-utils-0.7.2/src/sync/parker.rs","byte_start":8554479,"byte_end":8554485,"line_start":59,"line_end":59,"column_start":22,"column_end":28},"value":"","parent":null,"children":[],"docs":"","sig":null,"attributes":[]},{"id":28,"kind":"Inherent","span":{"file_name":"/Users/rodydavis/.cargo/registry/src/github.com-1ecc6299db9ec823/crossbeam-utils-0.7.2/src/sync/parker.rs","byte_start":8554495,"byte_end":8554501,"line_start":61,"line_end":61,"column_start":6,"column_end":12},"value":"","parent":null,"children":[{"krate":0,"index":281},{"krate":0,"index":282},{"krate":0,"index":283},{"krate":0,"index":284}],"docs":"","sig":null,"attributes":[]},{"id":29,"kind":"Direct","span":{"file_name":"/Users/rodydavis/.cargo/registry/src/github.com-1ecc6299db9ec823/crossbeam-utils-0.7.2/src/sync/parker.rs","byte_start":8557083,"byte_end":8557089,"line_start":155,"line_end":155,"column_start":21,"column_end":27},"value":"","parent":null,"children":[{"krate":0,"index":286}],"docs":"","sig":null,"attributes":[]},{"id":30,"kind":"Direct","span":{"file_name":"/Users/rodydavis/.cargo/registry/src/github.com-1ecc6299db9ec823/crossbeam-utils-0.7.2/src/sync/parker.rs","byte_start":8557357,"byte_end":8557365,"line_start":168,"line_end":168,"column_start":22,"column_end":30},"value":"","parent":null,"children":[],"docs":"","sig":null,"attributes":[]},{"id":31,"kind":"Direct","span":{"file_name":"/Users/rodydavis/.cargo/registry/src/github.com-1ecc6299db9ec823/crossbeam-utils-0.7.2/src/sync/parker.rs","byte_start":8557390,"byte_end":8557398,"line_start":169,"line_end":169,"column_start":22,"column_end":30},"value":"","parent":null,"children":[],"docs":"","sig":null,"attributes":[]},{"id":32,"kind":"Inherent","span":{"file_name":"/Users/rodydavis/.cargo/registry/src/github.com-1ecc6299db9ec823/crossbeam-utils-0.7.2/src/sync/parker.rs","byte_start":8557408,"byte_end":8557416,"line_start":171,"line_end":171,"column_start":6,"column_end":14},"value":"","parent":null,"children":[{"krate":0,"index":292}],"docs":"","sig":null,"attributes":[]},{"id":33,"kind":"Direct","span":{"file_name":"/Users/rodydavis/.cargo/registry/src/github.com-1ecc6299db9ec823/crossbeam-utils-0.7.2/src/sync/parker.rs","byte_start":8558350,"byte_end":8558358,"line_start":204,"line_end":204,"column_start":21,"column_end":29},"value":"","parent":null,"children":[{"krate":0,"index":294}],"docs":"","sig":null,"attributes":[]},{"id":34,"kind":"Direct","span":{"file_name":"/Users/rodydavis/.cargo/registry/src/github.com-1ecc6299db9ec823/crossbeam-utils-0.7.2/src/sync/parker.rs","byte_start":8558477,"byte_end":8558485,"line_start":210,"line_end":210,"column_start":16,"column_end":24},"value":"","parent":null,"children":[{"krate":0,"index":296}],"docs":"","sig":null,"attributes":[]},{"id":35,"kind":"Inherent","span":{"file_name":"/Users/rodydavis/.cargo/registry/src/github.com-1ecc6299db9ec823/crossbeam-utils-0.7.2/src/sync/parker.rs","byte_start":8558763,"byte_end":8558768,"line_start":228,"line_end":228,"column_start":6,"column_end":11},"value":"","parent":null,"children":[{"krate":0,"index":305},{"krate":0,"index":306}],"docs":"","sig":null,"attributes":[]},{"id":36,"kind":"Direct","span":{"file_name":"/Users/rodydavis/.cargo/registry/src/github.com-1ecc6299db9ec823/crossbeam-utils-0.7.2/src/sync/sharded_lock.rs","byte_start":8565837,"byte_end":8565848,"line_start":83,"line_end":83,"column_start":40,"column_end":51},"value":"","parent":null,"children":[],"docs":"","sig":null,"attributes":[]},{"id":37,"kind":"Direct","span":{"file_name":"/Users/rodydavis/.cargo/registry/src/github.com-1ecc6299db9ec823/crossbeam-utils-0.7.2/src/sync/sharded_lock.rs","byte_start":8565901,"byte_end":8565912,"line_start":84,"line_end":84,"column_start":47,"column_end":58},"value":"","parent":null,"children":[],"docs":"","sig":null,"attributes":[]},{"id":38,"kind":"Direct","span":{"file_name":"/Users/rodydavis/.cargo/registry/src/github.com-1ecc6299db9ec823/crossbeam-utils-0.7.2/src/sync/sharded_lock.rs","byte_start":8565951,"byte_end":8565962,"line_start":86,"line_end":86,"column_start":32,"column_end":43},"value":"","parent":null,"children":[],"docs":"","sig":null,"attributes":[]},{"id":39,"kind":"Direct","span":{"file_name":"/Users/rodydavis/.cargo/registry/src/github.com-1ecc6299db9ec823/crossbeam-utils-0.7.2/src/sync/sharded_lock.rs","byte_start":8566003,"byte_end":8566014,"line_start":87,"line_end":87,"column_start":35,"column_end":46},"value":"","parent":null,"children":[],"docs":"","sig":null,"attributes":[]},{"id":40,"kind":"Inherent","span":{"file_name":"/Users/rodydavis/.cargo/registry/src/github.com-1ecc6299db9ec823/crossbeam-utils-0.7.2/src/sync/sharded_lock.rs","byte_start":8566030,"byte_end":8566041,"line_start":89,"line_end":89,"column_start":9,"column_end":20},"value":"","parent":null,"children":[{"krate":0,"index":351},{"krate":0,"index":353}],"docs":"","sig":null,"attributes":[]},{"id":41,"kind":"Inherent","span":{"file_name":"/Users/rodydavis/.cargo/registry/src/github.com-1ecc6299db9ec823/crossbeam-utils-0.7.2/src/sync/sharded_lock.rs","byte_start":8567516,"byte_end":8567527,"line_start":143,"line_end":143,"column_start":17,"column_end":28},"value":"","parent":null,"children":[{"krate":0,"index":356},{"krate":0,"index":357},{"krate":0,"index":358},{"krate":0,"index":359},{"krate":0,"index":360},{"krate":0,"index":361}],"docs":"","sig":null,"attributes":[]},{"id":42,"kind":"Direct","span":{"file_name":"/Users/rodydavis/.cargo/registry/src/github.com-1ecc6299db9ec823/crossbeam-utils-0.7.2/src/sync/sharded_lock.rs","byte_start":8577225,"byte_end":8577236,"line_start":418,"line_end":418,"column_start":45,"column_end":56},"value":"","parent":null,"children":[{"krate":0,"index":364}],"docs":"","sig":null,"attributes":[]},{"id":43,"kind":"Direct","span":{"file_name":"/Users/rodydavis/.cargo/registry/src/github.com-1ecc6299db9ec823/crossbeam-utils-0.7.2/src/sync/sharded_lock.rs","byte_start":8577770,"byte_end":8577787,"line_start":431,"line_end":431,"column_start":37,"column_end":54},"value":"","parent":null,"children":[{"krate":0,"index":368}],"docs":"","sig":null,"attributes":[]},{"id":44,"kind":"Direct","span":{"file_name":"/Users/rodydavis/.cargo/registry/src/github.com-1ecc6299db9ec823/crossbeam-utils-0.7.2/src/sync/sharded_lock.rs","byte_start":8578146,"byte_end":8578157,"line_start":444,"line_end":444,"column_start":30,"column_end":41},"value":"","parent":null,"children":[{"krate":0,"index":371}],"docs":"","sig":null,"attributes":[]},{"id":45,"kind":"Direct","span":{"file_name":"/Users/rodydavis/.cargo/registry/src/github.com-1ecc6299db9ec823/crossbeam-utils-0.7.2/src/sync/sharded_lock.rs","byte_start":8578274,"byte_end":8578285,"line_start":450,"line_end":450,"column_start":21,"column_end":32},"value":"","parent":null,"children":[{"krate":0,"index":374}],"docs":"","sig":null,"attributes":[]},{"id":46,"kind":"Direct","span":{"file_name":"/Users/rodydavis/.cargo/registry/src/github.com-1ecc6299db9ec823/crossbeam-utils-0.7.2/src/sync/sharded_lock.rs","byte_start":8578708,"byte_end":8578728,"line_start":465,"line_end":465,"column_start":44,"column_end":64},"value":"","parent":null,"children":[],"docs":"","sig":null,"attributes":[]},{"id":47,"kind":"Direct","span":{"file_name":"/Users/rodydavis/.cargo/registry/src/github.com-1ecc6299db9ec823/crossbeam-utils-0.7.2/src/sync/sharded_lock.rs","byte_start":8578770,"byte_end":8578790,"line_start":467,"line_end":467,"column_start":31,"column_end":51},"value":"","parent":null,"children":[{"krate":0,"index":387},{"krate":0,"index":388}],"docs":"","sig":null,"attributes":[]},{"id":48,"kind":"Direct","span":{"file_name":"/Users/rodydavis/.cargo/registry/src/github.com-1ecc6299db9ec823/crossbeam-utils-0.7.2/src/sync/sharded_lock.rs","byte_start":8578941,"byte_end":8578961,"line_start":475,"line_end":475,"column_start":40,"column_end":60},"value":"","parent":null,"children":[{"krate":0,"index":392}],"docs":"","sig":null,"attributes":[]},{"id":49,"kind":"Direct","span":{"file_name":"/Users/rodydavis/.cargo/registry/src/github.com-1ecc6299db9ec823/crossbeam-utils-0.7.2/src/sync/sharded_lock.rs","byte_start":8579199,"byte_end":8579219,"line_start":483,"line_end":483,"column_start":53,"column_end":73},"value":"","parent":null,"children":[{"krate":0,"index":396}],"docs":"","sig":null,"attributes":[]},{"id":50,"kind":"Direct","span":{"file_name":"/Users/rodydavis/.cargo/registry/src/github.com-1ecc6299db9ec823/crossbeam-utils-0.7.2/src/sync/sharded_lock.rs","byte_start":8579642,"byte_end":8579663,"line_start":497,"line_end":497,"column_start":44,"column_end":65},"value":"","parent":null,"children":[],"docs":"","sig":null,"attributes":[]},{"id":51,"kind":"Direct","span":{"file_name":"/Users/rodydavis/.cargo/registry/src/github.com-1ecc6299db9ec823/crossbeam-utils-0.7.2/src/sync/sharded_lock.rs","byte_start":8579704,"byte_end":8579725,"line_start":499,"line_end":499,"column_start":30,"column_end":51},"value":"","parent":null,"children":[{"krate":0,"index":408}],"docs":"","sig":null,"attributes":[]},{"id":52,"kind":"Direct","span":{"file_name":"/Users/rodydavis/.cargo/registry/src/github.com-1ecc6299db9ec823/crossbeam-utils-0.7.2/src/sync/sharded_lock.rs","byte_start":8580113,"byte_end":8580134,"line_start":512,"line_end":512,"column_start":40,"column_end":61},"value":"","parent":null,"children":[{"krate":0,"index":412}],"docs":"","sig":null,"attributes":[]},{"id":53,"kind":"Direct","span":{"file_name":"/Users/rodydavis/.cargo/registry/src/github.com-1ecc6299db9ec823/crossbeam-utils-0.7.2/src/sync/sharded_lock.rs","byte_start":8580373,"byte_end":8580394,"line_start":520,"line_end":520,"column_start":53,"column_end":74},"value":"","parent":null,"children":[{"krate":0,"index":416}],"docs":"","sig":null,"attributes":[]},{"id":54,"kind":"Direct","span":{"file_name":"/Users/rodydavis/.cargo/registry/src/github.com-1ecc6299db9ec823/crossbeam-utils-0.7.2/src/sync/sharded_lock.rs","byte_start":8580526,"byte_end":8580547,"line_start":526,"line_end":526,"column_start":31,"column_end":52},"value":"","parent":null,"children":[{"krate":0,"index":420},{"krate":0,"index":421}],"docs":"","sig":null,"attributes":[]},{"id":55,"kind":"Direct","span":{"file_name":"/Users/rodydavis/.cargo/registry/src/github.com-1ecc6299db9ec823/crossbeam-utils-0.7.2/src/sync/sharded_lock.rs","byte_start":8580692,"byte_end":8580713,"line_start":534,"line_end":534,"column_start":34,"column_end":55},"value":"","parent":null,"children":[{"krate":0,"index":425}],"docs":"","sig":null,"attributes":[]},{"id":56,"kind":"Direct","span":{"file_name":"/Users/rodydavis/.cargo/registry/src/github.com-1ecc6299db9ec823/crossbeam-utils-0.7.2/src/sync/sharded_lock.rs","byte_start":8582011,"byte_end":8582023,"line_start":580,"line_end":580,"column_start":15,"column_end":27},"value":"","parent":null,"children":[{"krate":0,"index":436}],"docs":"","sig":null,"attributes":[]},{"id":57,"kind":"Inherent","span":{"file_name":"/Users/rodydavis/.cargo/registry/src/github.com-1ecc6299db9ec823/crossbeam-utils-0.7.2/src/sync/wait_group.rs","byte_start":8584174,"byte_end":8584183,"line_start":55,"line_end":55,"column_start":6,"column_end":15},"value":"","parent":null,"children":[{"krate":0,"index":449},{"krate":0,"index":450}],"docs":"","sig":null,"attributes":[]},{"id":58,"kind":"Direct","span":{"file_name":"/Users/rodydavis/.cargo/registry/src/github.com-1ecc6299db9ec823/crossbeam-utils-0.7.2/src/sync/wait_group.rs","byte_start":8585483,"byte_end":8585492,"line_start":110,"line_end":110,"column_start":15,"column_end":24},"value":"","parent":null,"children":[{"krate":0,"index":452}],"docs":"","sig":null,"attributes":[]},{"id":59,"kind":"Direct","span":{"file_name":"/Users/rodydavis/.cargo/registry/src/github.com-1ecc6299db9ec823/crossbeam-utils-0.7.2/src/sync/wait_group.rs","byte_start":8585701,"byte_end":8585710,"line_start":121,"line_end":121,"column_start":16,"column_end":25},"value":"","parent":null,"children":[{"krate":0,"index":454}],"docs":"","sig":null,"attributes":[]},{"id":60,"kind":"Direct","span":{"file_name":"/Users/rodydavis/.cargo/registry/src/github.com-1ecc6299db9ec823/crossbeam-utils-0.7.2/src/sync/wait_group.rs","byte_start":8585926,"byte_end":8585935,"line_start":132,"line_end":132,"column_start":21,"column_end":30},"value":"","parent":null,"children":[{"krate":0,"index":456}],"docs":"","sig":null,"attributes":[]},{"id":61,"kind":"Direct","span":{"file_name":"/Users/rodydavis/.cargo/registry/src/github.com-1ecc6299db9ec823/crossbeam-utils-0.7.2/src/thread.rs","byte_start":8592321,"byte_end":8592326,"line_start":208,"line_end":208,"column_start":28,"column_end":33},"value":"","parent":null,"children":[],"docs":"","sig":null,"attributes":[]},{"id":62,"kind":"Inherent","span":{"file_name":"/Users/rodydavis/.cargo/registry/src/github.com-1ecc6299db9ec823/crossbeam-utils-0.7.2/src/thread.rs","byte_start":8592348,"byte_end":8592353,"line_start":210,"line_end":210,"column_start":12,"column_end":17},"value":"","parent":null,"children":[{"krate":0,"index":496},{"krate":0,"index":500}],"docs":"","sig":null,"attributes":[]},{"id":63,"kind":"Direct","span":{"file_name":"/Users/rodydavis/.cargo/registry/src/github.com-1ecc6299db9ec823/crossbeam-utils-0.7.2/src/thread.rs","byte_start":8594240,"byte_end":8594245,"line_start":271,"line_end":271,"column_start":27,"column_end":32},"value":"","parent":null,"children":[{"krate":0,"index":504}],"docs":"","sig":null,"attributes":[]},{"id":64,"kind":"Inherent","span":{"file_name":"/Users/rodydavis/.cargo/registry/src/github.com-1ecc6299db9ec823/crossbeam-utils-0.7.2/src/thread.rs","byte_start":8595821,"byte_end":8595840,"line_start":316,"line_end":316,"column_start":20,"column_end":39},"value":"","parent":null,"children":[{"krate":0,"index":508},{"krate":0,"index":509},{"krate":0,"index":510}],"docs":"","sig":null,"attributes":[]},{"id":65,"kind":"Direct","span":{"file_name":"/Users/rodydavis/.cargo/registry/src/github.com-1ecc6299db9ec823/crossbeam-utils-0.7.2/src/thread.rs","byte_start":8600276,"byte_end":8600292,"line_start":451,"line_end":451,"column_start":33,"column_end":49},"value":"","parent":null,"children":[],"docs":"","sig":null,"attributes":[]},{"id":66,"kind":"Direct","span":{"file_name":"/Users/rodydavis/.cargo/registry/src/github.com-1ecc6299db9ec823/crossbeam-utils-0.7.2/src/thread.rs","byte_start":8600339,"byte_end":8600355,"line_start":452,"line_end":452,"column_start":33,"column_end":49},"value":"","parent":null,"children":[],"docs":"","sig":null,"attributes":[]},{"id":67,"kind":"Inherent","span":{"file_name":"/Users/rodydavis/.cargo/registry/src/github.com-1ecc6299db9ec823/crossbeam-utils-0.7.2/src/thread.rs","byte_start":8600829,"byte_end":8600845,"line_start":469,"line_end":469,"column_start":17,"column_end":33},"value":"","parent":null,"children":[{"krate":0,"index":532},{"krate":0,"index":534}],"docs":"","sig":null,"attributes":[]},{"id":68,"kind":"Direct","span":{"file_name":"/Users/rodydavis/.cargo/registry/src/github.com-1ecc6299db9ec823/crossbeam-utils-0.7.2/src/thread.rs","byte_start":8602684,"byte_end":8602700,"line_start":525,"line_end":525,"column_start":32,"column_end":48},"value":"","parent":null,"children":[{"krate":0,"index":538}],"docs":"","sig":null,"attributes":[]}],"refs":[{"kind":"Mod","span":{"file_name":"/Users/rodydavis/.cargo/registry/src/github.com-1ecc6299db9ec823/crossbeam-utils-0.7.2/src/lib.rs","byte_start":1568,"byte_end":1574,"line_start":48,"line_end":48,"column_start":9,"column_end":15},"ref_id":{"krate":0,"index":5}},{"kind":"Mod","span":{"file_name":"/Users/rodydavis/.cargo/registry/src/github.com-1ecc6299db9ec823/crossbeam-utils-0.7.2/src/lib.rs","byte_start":1786,"byte_end":1790,"line_start":61,"line_end":61,"column_start":17,"column_end":21},"ref_id":{"krate":0,"index":265}},{"kind":"Mod","span":{"file_name":"/Users/rodydavis/.cargo/registry/src/github.com-1ecc6299db9ec823/crossbeam-utils-0.7.2/src/lib.rs","byte_start":1808,"byte_end":1814,"line_start":62,"line_end":62,"column_start":17,"column_end":23},"ref_id":{"krate":0,"index":465}}],"macro_refs":[],"relations":[{"span":{"file_name":"/Users/rodydavis/.cargo/registry/src/github.com-1ecc6299db9ec823/crossbeam-utils-0.7.2/src/atomic/seq_lock.rs","byte_start":8549884,"byte_end":8549891,"line_start":14,"line_end":14,"column_start":6,"column_end":13},"kind":{"Impl":{"id":0}},"from":{"krate":0,"index":154},"to":{"krate":4294967295,"index":4294967295}},{"span":{"file_name":"/Users/rodydavis/.cargo/registry/src/github.com-1ecc6299db9ec823/crossbeam-utils-0.7.2/src/atomic/seq_lock.rs","byte_start":8551474,"byte_end":8551491,"line_start":72,"line_end":72,"column_start":6,"column_end":23},"kind":{"Impl":{"id":1}},"from":{"krate":0,"index":161},"to":{"krate":4294967295,"index":4294967295}},{"span":{"file_name":"/Users/rodydavis/.cargo/registry/src/github.com-1ecc6299db9ec823/crossbeam-utils-0.7.2/src/atomic/seq_lock.rs","byte_start":8551676,"byte_end":8551693,"line_start":80,"line_end":80,"column_start":15,"column_end":32},"kind":{"Impl":{"id":2}},"from":{"krate":0,"index":161},"to":{"krate":2,"index":1726}},{"span":{"file_name":"/Users/rodydavis/.cargo/registry/src/github.com-1ecc6299db9ec823/crossbeam-utils-0.7.2/src/atomic/atomic_cell.rs","byte_start":4064,"byte_end":4074,"line_start":36,"line_end":36,"column_start":31,"column_end":41},"kind":{"Impl":{"id":3}},"from":{"krate":0,"index":19},"to":{"krate":2,"index":1533}},{"span":{"file_name":"/Users/rodydavis/.cargo/registry/src/github.com-1ecc6299db9ec823/crossbeam-utils-0.7.2/src/atomic/atomic_cell.rs","byte_start":4111,"byte_end":4121,"line_start":37,"line_end":37,"column_start":31,"column_end":41},"kind":{"Impl":{"id":4}},"from":{"krate":0,"index":19},"to":{"krate":2,"index":1545}},{"span":{"file_name":"/Users/rodydavis/.cargo/registry/src/github.com-1ecc6299db9ec823/crossbeam-utils-0.7.2/src/atomic/atomic_cell.rs","byte_start":4176,"byte_end":4186,"line_start":40,"line_end":40,"column_start":24,"column_end":34},"kind":{"Impl":{"id":5}},"from":{"krate":0,"index":19},"to":{"krate":1,"index":3706}},{"span":{"file_name":"/Users/rodydavis/.cargo/registry/src/github.com-1ecc6299db9ec823/crossbeam-utils-0.7.2/src/atomic/atomic_cell.rs","byte_start":4243,"byte_end":4253,"line_start":42,"line_end":42,"column_start":27,"column_end":37},"kind":{"Impl":{"id":6}},"from":{"krate":0,"index":19},"to":{"krate":1,"index":3707}},{"span":{"file_name":"/Users/rodydavis/.cargo/registry/src/github.com-1ecc6299db9ec823/crossbeam-utils-0.7.2/src/atomic/atomic_cell.rs","byte_start":4269,"byte_end":4279,"line_start":44,"line_end":44,"column_start":9,"column_end":19},"kind":{"Impl":{"id":7}},"from":{"krate":0,"index":19},"to":{"krate":4294967295,"index":4294967295}},{"span":{"file_name":"/Users/rodydavis/.cargo/registry/src/github.com-1ecc6299db9ec823/crossbeam-utils-0.7.2/src/atomic/atomic_cell.rs","byte_start":7628,"byte_end":7638,"line_start":166,"line_end":166,"column_start":17,"column_end":27},"kind":{"Impl":{"id":8}},"from":{"krate":0,"index":19},"to":{"krate":4294967295,"index":4294967295}},{"span":{"file_name":"/Users/rodydavis/.cargo/registry/src/github.com-1ecc6299db9ec823/crossbeam-utils-0.7.2/src/atomic/atomic_cell.rs","byte_start":8495,"byte_end":8505,"line_start":202,"line_end":202,"column_start":18,"column_end":28},"kind":{"Impl":{"id":9}},"from":{"krate":0,"index":19},"to":{"krate":4294967295,"index":4294967295}},{"span":{"file_name":"/Users/rodydavis/.cargo/registry/src/github.com-1ecc6299db9ec823/crossbeam-utils-0.7.2/src/atomic/atomic_cell.rs","byte_start":8946,"byte_end":8956,"line_start":221,"line_end":221,"column_start":15,"column_end":25},"kind":{"Impl":{"id":10}},"from":{"krate":0,"index":19},"to":{"krate":4294967295,"index":4294967295}},{"span":{"file_name":"/Users/rodydavis/.cargo/registry/src/github.com-1ecc6299db9ec823/crossbeam-utils-0.7.2/src/atomic/atomic_cell.rs","byte_start":9285,"byte_end":9295,"line_start":238,"line_end":238,"column_start":20,"column_end":30},"kind":{"Impl":{"id":11}},"from":{"krate":0,"index":19},"to":{"krate":4294967295,"index":4294967295}},{"span":{"file_name":"/Users/rodydavis/.cargo/registry/src/github.com-1ecc6299db9ec823/crossbeam-utils-0.7.2/src/atomic/atomic_cell.rs","byte_start":20509,"byte_end":20519,"line_start":556,"line_end":556,"column_start":6,"column_end":16},"kind":{"Impl":{"id":12}},"from":{"krate":0,"index":19},"to":{"krate":4294967295,"index":4294967295}},{"span":{"file_name":"/Users/rodydavis/.cargo/registry/src/github.com-1ecc6299db9ec823/crossbeam-utils-0.7.2/src/atomic/atomic_cell.rs","byte_start":22360,"byte_end":22370,"line_start":621,"line_end":621,"column_start":30,"column_end":40},"kind":{"Impl":{"id":13}},"from":{"krate":0,"index":19},"to":{"krate":2,"index":2206}},{"span":{"file_name":"/Users/rodydavis/.cargo/registry/src/github.com-1ecc6299db9ec823/crossbeam-utils-0.7.2/src/atomic/atomic_cell.rs","byte_start":22501,"byte_end":22511,"line_start":627,"line_end":627,"column_start":43,"column_end":53},"kind":{"Impl":{"id":14}},"from":{"krate":0,"index":19},"to":{"krate":2,"index":7636}},{"span":{"file_name":"/Users/rodydavis/.cargo/registry/src/github.com-1ecc6299db9ec823/crossbeam-utils-0.7.2/src/atomic/atomic_cell.rs","byte_start":25262,"byte_end":25272,"line_start":695,"line_end":695,"column_start":6,"column_end":16},"kind":{"Impl":{"id":15}},"from":{"krate":0,"index":70},"to":{"krate":4294967295,"index":4294967295}},{"span":{"file_name":"/Users/rodydavis/.cargo/registry/src/github.com-1ecc6299db9ec823/crossbeam-utils-0.7.2/src/atomic/consume.rs","byte_start":34548,"byte_end":34557,"line_start":79,"line_end":79,"column_start":49,"column_end":58},"kind":{"Impl":{"id":16}},"from":{"krate":2,"index":2722},"to":{"krate":0,"index":90}},{"span":{"file_name":"/Users/rodydavis/.cargo/registry/src/github.com-1ecc6299db9ec823/crossbeam-utils-0.7.2/src/cache_padded.rs","byte_start":37333,"byte_end":37344,"line_start":72,"line_end":72,"column_start":31,"column_end":42},"kind":{"Impl":{"id":17}},"from":{"krate":0,"index":238},"to":{"krate":2,"index":1533}},{"span":{"file_name":"/Users/rodydavis/.cargo/registry/src/github.com-1ecc6299db9ec823/crossbeam-utils-0.7.2/src/cache_padded.rs","byte_start":37381,"byte_end":37392,"line_start":73,"line_end":73,"column_start":31,"column_end":42},"kind":{"Impl":{"id":18}},"from":{"krate":0,"index":238},"to":{"krate":2,"index":1545}},{"span":{"file_name":"/Users/rodydavis/.cargo/registry/src/github.com-1ecc6299db9ec823/crossbeam-utils-0.7.2/src/cache_padded.rs","byte_start":37408,"byte_end":37419,"line_start":75,"line_end":75,"column_start":9,"column_end":20},"kind":{"Impl":{"id":19}},"from":{"krate":0,"index":238},"to":{"krate":4294967295,"index":4294967295}},{"span":{"file_name":"/Users/rodydavis/.cargo/registry/src/github.com-1ecc6299db9ec823/crossbeam-utils-0.7.2/src/cache_padded.rs","byte_start":38079,"byte_end":38090,"line_start":105,"line_end":105,"column_start":19,"column_end":30},"kind":{"Impl":{"id":20}},"from":{"krate":0,"index":238},"to":{"krate":2,"index":1704}},{"span":{"file_name":"/Users/rodydavis/.cargo/registry/src/github.com-1ecc6299db9ec823/crossbeam-utils-0.7.2/src/cache_padded.rs","byte_start":38196,"byte_end":38207,"line_start":113,"line_end":113,"column_start":22,"column_end":33},"kind":{"Impl":{"id":21}},"from":{"krate":0,"index":238},"to":{"krate":2,"index":1715}},{"span":{"file_name":"/Users/rodydavis/.cargo/registry/src/github.com-1ecc6299db9ec823/crossbeam-utils-0.7.2/src/cache_padded.rs","byte_start":38321,"byte_end":38332,"line_start":119,"line_end":119,"column_start":36,"column_end":47},"kind":{"Impl":{"id":22}},"from":{"krate":0,"index":238},"to":{"krate":2,"index":7636}},{"span":{"file_name":"/Users/rodydavis/.cargo/registry/src/github.com-1ecc6299db9ec823/crossbeam-utils-0.7.2/src/cache_padded.rs","byte_start":38527,"byte_end":38538,"line_start":127,"line_end":127,"column_start":21,"column_end":32},"kind":{"Impl":{"id":23}},"from":{"krate":0,"index":238},"to":{"krate":2,"index":2258}},{"span":{"file_name":"/Users/rodydavis/.cargo/registry/src/github.com-1ecc6299db9ec823/crossbeam-utils-0.7.2/src/backoff.rs","byte_start":41129,"byte_end":41136,"line_start":84,"line_end":84,"column_start":6,"column_end":13},"kind":{"Impl":{"id":24}},"from":{"krate":0,"index":133},"to":{"krate":4294967295,"index":4294967295}},{"span":{"file_name":"/Users/rodydavis/.cargo/registry/src/github.com-1ecc6299db9ec823/crossbeam-utils-0.7.2/src/backoff.rs","byte_start":46771,"byte_end":46778,"line_start":279,"line_end":279,"column_start":21,"column_end":28},"kind":{"Impl":{"id":25}},"from":{"krate":0,"index":133},"to":{"krate":2,"index":7636}},{"span":{"file_name":"/Users/rodydavis/.cargo/registry/src/github.com-1ecc6299db9ec823/crossbeam-utils-0.7.2/src/backoff.rs","byte_start":47018,"byte_end":47025,"line_start":288,"line_end":288,"column_start":18,"column_end":25},"kind":{"Impl":{"id":26}},"from":{"krate":0,"index":133},"to":{"krate":2,"index":2206}},{"span":{"file_name":"/Users/rodydavis/.cargo/registry/src/github.com-1ecc6299db9ec823/crossbeam-utils-0.7.2/src/sync/parker.rs","byte_start":8554479,"byte_end":8554485,"line_start":59,"line_end":59,"column_start":22,"column_end":28},"kind":{"Impl":{"id":27}},"from":{"krate":0,"index":276},"to":{"krate":2,"index":1533}},{"span":{"file_name":"/Users/rodydavis/.cargo/registry/src/github.com-1ecc6299db9ec823/crossbeam-utils-0.7.2/src/sync/parker.rs","byte_start":8554495,"byte_end":8554501,"line_start":61,"line_end":61,"column_start":6,"column_end":12},"kind":{"Impl":{"id":28}},"from":{"krate":0,"index":276},"to":{"krate":4294967295,"index":4294967295}},{"span":{"file_name":"/Users/rodydavis/.cargo/registry/src/github.com-1ecc6299db9ec823/crossbeam-utils-0.7.2/src/sync/parker.rs","byte_start":8557083,"byte_end":8557089,"line_start":155,"line_end":155,"column_start":21,"column_end":27},"kind":{"Impl":{"id":29}},"from":{"krate":0,"index":276},"to":{"krate":2,"index":7636}},{"span":{"file_name":"/Users/rodydavis/.cargo/registry/src/github.com-1ecc6299db9ec823/crossbeam-utils-0.7.2/src/sync/parker.rs","byte_start":8557357,"byte_end":8557365,"line_start":168,"line_end":168,"column_start":22,"column_end":30},"kind":{"Impl":{"id":30}},"from":{"krate":0,"index":287},"to":{"krate":2,"index":1533}},{"span":{"file_name":"/Users/rodydavis/.cargo/registry/src/github.com-1ecc6299db9ec823/crossbeam-utils-0.7.2/src/sync/parker.rs","byte_start":8557390,"byte_end":8557398,"line_start":169,"line_end":169,"column_start":22,"column_end":30},"kind":{"Impl":{"id":31}},"from":{"krate":0,"index":287},"to":{"krate":2,"index":1545}},{"span":{"file_name":"/Users/rodydavis/.cargo/registry/src/github.com-1ecc6299db9ec823/crossbeam-utils-0.7.2/src/sync/parker.rs","byte_start":8557408,"byte_end":8557416,"line_start":171,"line_end":171,"column_start":6,"column_end":14},"kind":{"Impl":{"id":32}},"from":{"krate":0,"index":287},"to":{"krate":4294967295,"index":4294967295}},{"span":{"file_name":"/Users/rodydavis/.cargo/registry/src/github.com-1ecc6299db9ec823/crossbeam-utils-0.7.2/src/sync/parker.rs","byte_start":8558350,"byte_end":8558358,"line_start":204,"line_end":204,"column_start":21,"column_end":29},"kind":{"Impl":{"id":33}},"from":{"krate":0,"index":287},"to":{"krate":2,"index":7636}},{"span":{"file_name":"/Users/rodydavis/.cargo/registry/src/github.com-1ecc6299db9ec823/crossbeam-utils-0.7.2/src/sync/parker.rs","byte_start":8558477,"byte_end":8558485,"line_start":210,"line_end":210,"column_start":16,"column_end":24},"kind":{"Impl":{"id":34}},"from":{"krate":0,"index":287},"to":{"krate":2,"index":2181}},{"span":{"file_name":"/Users/rodydavis/.cargo/registry/src/github.com-1ecc6299db9ec823/crossbeam-utils-0.7.2/src/sync/parker.rs","byte_start":8558763,"byte_end":8558768,"line_start":228,"line_end":228,"column_start":6,"column_end":11},"kind":{"Impl":{"id":35}},"from":{"krate":0,"index":300},"to":{"krate":4294967295,"index":4294967295}},{"span":{"file_name":"/Users/rodydavis/.cargo/registry/src/github.com-1ecc6299db9ec823/crossbeam-utils-0.7.2/src/sync/sharded_lock.rs","byte_start":8565837,"byte_end":8565848,"line_start":83,"line_end":83,"column_start":40,"column_end":51},"kind":{"Impl":{"id":36}},"from":{"krate":0,"index":337},"to":{"krate":2,"index":1533}},{"span":{"file_name":"/Users/rodydavis/.cargo/registry/src/github.com-1ecc6299db9ec823/crossbeam-utils-0.7.2/src/sync/sharded_lock.rs","byte_start":8565901,"byte_end":8565912,"line_start":84,"line_end":84,"column_start":47,"column_end":58},"kind":{"Impl":{"id":37}},"from":{"krate":0,"index":337},"to":{"krate":2,"index":1545}},{"span":{"file_name":"/Users/rodydavis/.cargo/registry/src/github.com-1ecc6299db9ec823/crossbeam-utils-0.7.2/src/sync/sharded_lock.rs","byte_start":8565951,"byte_end":8565962,"line_start":86,"line_end":86,"column_start":32,"column_end":43},"kind":{"Impl":{"id":38}},"from":{"krate":0,"index":337},"to":{"krate":1,"index":3706}},{"span":{"file_name":"/Users/rodydavis/.cargo/registry/src/github.com-1ecc6299db9ec823/crossbeam-utils-0.7.2/src/sync/sharded_lock.rs","byte_start":8566003,"byte_end":8566014,"line_start":87,"line_end":87,"column_start":35,"column_end":46},"kind":{"Impl":{"id":39}},"from":{"krate":0,"index":337},"to":{"krate":1,"index":3707}},{"span":{"file_name":"/Users/rodydavis/.cargo/registry/src/github.com-1ecc6299db9ec823/crossbeam-utils-0.7.2/src/sync/sharded_lock.rs","byte_start":8566030,"byte_end":8566041,"line_start":89,"line_end":89,"column_start":9,"column_end":20},"kind":{"Impl":{"id":40}},"from":{"krate":0,"index":337},"to":{"krate":4294967295,"index":4294967295}},{"span":{"file_name":"/Users/rodydavis/.cargo/registry/src/github.com-1ecc6299db9ec823/crossbeam-utils-0.7.2/src/sync/sharded_lock.rs","byte_start":8567516,"byte_end":8567527,"line_start":143,"line_end":143,"column_start":17,"column_end":28},"kind":{"Impl":{"id":41}},"from":{"krate":0,"index":337},"to":{"krate":4294967295,"index":4294967295}},{"span":{"file_name":"/Users/rodydavis/.cargo/registry/src/github.com-1ecc6299db9ec823/crossbeam-utils-0.7.2/src/sync/sharded_lock.rs","byte_start":8577225,"byte_end":8577236,"line_start":418,"line_end":418,"column_start":45,"column_end":56},"kind":{"Impl":{"id":42}},"from":{"krate":0,"index":337},"to":{"krate":2,"index":7636}},{"span":{"file_name":"/Users/rodydavis/.cargo/registry/src/github.com-1ecc6299db9ec823/crossbeam-utils-0.7.2/src/sync/sharded_lock.rs","byte_start":8577770,"byte_end":8577787,"line_start":431,"line_end":431,"column_start":37,"column_end":54},"kind":{"Impl":{"id":43}},"from":{"krate":0,"index":365},"to":{"krate":2,"index":7636}},{"span":{"file_name":"/Users/rodydavis/.cargo/registry/src/github.com-1ecc6299db9ec823/crossbeam-utils-0.7.2/src/sync/sharded_lock.rs","byte_start":8578146,"byte_end":8578157,"line_start":444,"line_end":444,"column_start":30,"column_end":41},"kind":{"Impl":{"id":44}},"from":{"krate":0,"index":337},"to":{"krate":2,"index":2206}},{"span":{"file_name":"/Users/rodydavis/.cargo/registry/src/github.com-1ecc6299db9ec823/crossbeam-utils-0.7.2/src/sync/sharded_lock.rs","byte_start":8578274,"byte_end":8578285,"line_start":450,"line_end":450,"column_start":21,"column_end":32},"kind":{"Impl":{"id":45}},"from":{"krate":0,"index":337},"to":{"krate":2,"index":2258}},{"span":{"file_name":"/Users/rodydavis/.cargo/registry/src/github.com-1ecc6299db9ec823/crossbeam-utils-0.7.2/src/sync/sharded_lock.rs","byte_start":8578708,"byte_end":8578728,"line_start":465,"line_end":465,"column_start":44,"column_end":64},"kind":{"Impl":{"id":46}},"from":{"krate":0,"index":375},"to":{"krate":2,"index":1545}},{"span":{"file_name":"/Users/rodydavis/.cargo/registry/src/github.com-1ecc6299db9ec823/crossbeam-utils-0.7.2/src/sync/sharded_lock.rs","byte_start":8578770,"byte_end":8578790,"line_start":467,"line_end":467,"column_start":31,"column_end":51},"kind":{"Impl":{"id":47}},"from":{"krate":0,"index":375},"to":{"krate":2,"index":1704}},{"span":{"file_name":"/Users/rodydavis/.cargo/registry/src/github.com-1ecc6299db9ec823/crossbeam-utils-0.7.2/src/sync/sharded_lock.rs","byte_start":8578941,"byte_end":8578961,"line_start":475,"line_end":475,"column_start":40,"column_end":60},"kind":{"Impl":{"id":48}},"from":{"krate":0,"index":375},"to":{"krate":2,"index":7636}},{"span":{"file_name":"/Users/rodydavis/.cargo/registry/src/github.com-1ecc6299db9ec823/crossbeam-utils-0.7.2/src/sync/sharded_lock.rs","byte_start":8579199,"byte_end":8579219,"line_start":483,"line_end":483,"column_start":53,"column_end":73},"kind":{"Impl":{"id":49}},"from":{"krate":0,"index":375},"to":{"krate":2,"index":7641}},{"span":{"file_name":"/Users/rodydavis/.cargo/registry/src/github.com-1ecc6299db9ec823/crossbeam-utils-0.7.2/src/sync/sharded_lock.rs","byte_start":8579642,"byte_end":8579663,"line_start":497,"line_end":497,"column_start":44,"column_end":65},"kind":{"Impl":{"id":50}},"from":{"krate":0,"index":397},"to":{"krate":2,"index":1545}},{"span":{"file_name":"/Users/rodydavis/.cargo/registry/src/github.com-1ecc6299db9ec823/crossbeam-utils-0.7.2/src/sync/sharded_lock.rs","byte_start":8579704,"byte_end":8579725,"line_start":499,"line_end":499,"column_start":30,"column_end":51},"kind":{"Impl":{"id":51}},"from":{"krate":0,"index":397},"to":{"krate":2,"index":1726}},{"span":{"file_name":"/Users/rodydavis/.cargo/registry/src/github.com-1ecc6299db9ec823/crossbeam-utils-0.7.2/src/sync/sharded_lock.rs","byte_start":8580113,"byte_end":8580134,"line_start":512,"line_end":512,"column_start":40,"column_end":61},"kind":{"Impl":{"id":52}},"from":{"krate":0,"index":397},"to":{"krate":2,"index":7636}},{"span":{"file_name":"/Users/rodydavis/.cargo/registry/src/github.com-1ecc6299db9ec823/crossbeam-utils-0.7.2/src/sync/sharded_lock.rs","byte_start":8580373,"byte_end":8580394,"line_start":520,"line_end":520,"column_start":53,"column_end":74},"kind":{"Impl":{"id":53}},"from":{"krate":0,"index":397},"to":{"krate":2,"index":7641}},{"span":{"file_name":"/Users/rodydavis/.cargo/registry/src/github.com-1ecc6299db9ec823/crossbeam-utils-0.7.2/src/sync/sharded_lock.rs","byte_start":8580526,"byte_end":8580547,"line_start":526,"line_end":526,"column_start":31,"column_end":52},"kind":{"Impl":{"id":54}},"from":{"krate":0,"index":397},"to":{"krate":2,"index":1704}},{"span":{"file_name":"/Users/rodydavis/.cargo/registry/src/github.com-1ecc6299db9ec823/crossbeam-utils-0.7.2/src/sync/sharded_lock.rs","byte_start":8580692,"byte_end":8580713,"line_start":534,"line_end":534,"column_start":34,"column_end":55},"kind":{"Impl":{"id":55}},"from":{"krate":0,"index":397},"to":{"krate":2,"index":1715}},{"span":{"file_name":"/Users/rodydavis/.cargo/registry/src/github.com-1ecc6299db9ec823/crossbeam-utils-0.7.2/src/sync/sharded_lock.rs","byte_start":8582011,"byte_end":8582023,"line_start":580,"line_end":580,"column_start":15,"column_end":27},"kind":{"Impl":{"id":56}},"from":{"krate":0,"index":432},"to":{"krate":2,"index":1726}},{"span":{"file_name":"/Users/rodydavis/.cargo/registry/src/github.com-1ecc6299db9ec823/crossbeam-utils-0.7.2/src/sync/wait_group.rs","byte_start":8584174,"byte_end":8584183,"line_start":55,"line_end":55,"column_start":6,"column_end":15},"kind":{"Impl":{"id":57}},"from":{"krate":0,"index":443},"to":{"krate":4294967295,"index":4294967295}},{"span":{"file_name":"/Users/rodydavis/.cargo/registry/src/github.com-1ecc6299db9ec823/crossbeam-utils-0.7.2/src/sync/wait_group.rs","byte_start":8585483,"byte_end":8585492,"line_start":110,"line_end":110,"column_start":15,"column_end":24},"kind":{"Impl":{"id":58}},"from":{"krate":0,"index":443},"to":{"krate":2,"index":1726}},{"span":{"file_name":"/Users/rodydavis/.cargo/registry/src/github.com-1ecc6299db9ec823/crossbeam-utils-0.7.2/src/sync/wait_group.rs","byte_start":8585701,"byte_end":8585710,"line_start":121,"line_end":121,"column_start":16,"column_end":25},"kind":{"Impl":{"id":59}},"from":{"krate":0,"index":443},"to":{"krate":2,"index":2181}},{"span":{"file_name":"/Users/rodydavis/.cargo/registry/src/github.com-1ecc6299db9ec823/crossbeam-utils-0.7.2/src/sync/wait_group.rs","byte_start":8585926,"byte_end":8585935,"line_start":132,"line_end":132,"column_start":21,"column_end":30},"kind":{"Impl":{"id":60}},"from":{"krate":0,"index":443},"to":{"krate":2,"index":7636}},{"span":{"file_name":"/Users/rodydavis/.cargo/registry/src/github.com-1ecc6299db9ec823/crossbeam-utils-0.7.2/src/thread.rs","byte_start":8592321,"byte_end":8592326,"line_start":208,"line_end":208,"column_start":28,"column_end":33},"kind":{"Impl":{"id":61}},"from":{"krate":0,"index":487},"to":{"krate":2,"index":1545}},{"span":{"file_name":"/Users/rodydavis/.cargo/registry/src/github.com-1ecc6299db9ec823/crossbeam-utils-0.7.2/src/thread.rs","byte_start":8592348,"byte_end":8592353,"line_start":210,"line_end":210,"column_start":12,"column_end":17},"kind":{"Impl":{"id":62}},"from":{"krate":0,"index":487},"to":{"krate":4294967295,"index":4294967295}},{"span":{"file_name":"/Users/rodydavis/.cargo/registry/src/github.com-1ecc6299db9ec823/crossbeam-utils-0.7.2/src/thread.rs","byte_start":8594240,"byte_end":8594245,"line_start":271,"line_end":271,"column_start":27,"column_end":32},"kind":{"Impl":{"id":63}},"from":{"krate":0,"index":487},"to":{"krate":2,"index":7636}},{"span":{"file_name":"/Users/rodydavis/.cargo/registry/src/github.com-1ecc6299db9ec823/crossbeam-utils-0.7.2/src/thread.rs","byte_start":8595821,"byte_end":8595840,"line_start":316,"line_end":316,"column_start":20,"column_end":39},"kind":{"Impl":{"id":64}},"from":{"krate":0,"index":554},"to":{"krate":4294967295,"index":4294967295}},{"span":{"file_name":"/Users/rodydavis/.cargo/registry/src/github.com-1ecc6299db9ec823/crossbeam-utils-0.7.2/src/thread.rs","byte_start":8600276,"byte_end":8600292,"line_start":451,"line_end":451,"column_start":33,"column_end":49},"kind":{"Impl":{"id":65}},"from":{"krate":0,"index":522},"to":{"krate":2,"index":1533}},{"span":{"file_name":"/Users/rodydavis/.cargo/registry/src/github.com-1ecc6299db9ec823/crossbeam-utils-0.7.2/src/thread.rs","byte_start":8600339,"byte_end":8600355,"line_start":452,"line_end":452,"column_start":33,"column_end":49},"kind":{"Impl":{"id":66}},"from":{"krate":0,"index":522},"to":{"krate":2,"index":1545}},{"span":{"file_name":"/Users/rodydavis/.cargo/registry/src/github.com-1ecc6299db9ec823/crossbeam-utils-0.7.2/src/thread.rs","byte_start":8600829,"byte_end":8600845,"line_start":469,"line_end":469,"column_start":17,"column_end":33},"kind":{"Impl":{"id":67}},"from":{"krate":0,"index":522},"to":{"krate":4294967295,"index":4294967295}},{"span":{"file_name":"/Users/rodydavis/.cargo/registry/src/github.com-1ecc6299db9ec823/crossbeam-utils-0.7.2/src/thread.rs","byte_start":8602684,"byte_end":8602700,"line_start":525,"line_end":525,"column_start":32,"column_end":48},"kind":{"Impl":{"id":68}},"from":{"krate":0,"index":522},"to":{"krate":2,"index":7636}}]}